Workbook

Sheet Léeme
B2: PROYECTO GESTORES — Ficha Integral de Iniciativa 2026
B3: Transformación del modelo operativo de Prestaciones y Reclamaciones · MVP Autorizaciones de Salud
B5: Qué cambió en esta versión | C5: Se incorporaron las definiciones de las sesiones del 18, 19 y 20 de agosto de 2026 (arranque de cronograma de releases, ejercicio de detalle funcional/técnico de Solicitud y Evaluación, y revisión técnica con Milton). Cada definición nueva se clasificó como requisito funcional (RF) o no funcional (RNF) y entró al plan y a la estimación. La columna 'Origen' permite distinguir lo que venía del archivo de requisitos v2 de lo nuevo.
B6: Sprint 0 — septiembre 2026 | C6: Antes de cualquier implementación hay un Sprint 0 que ocupa todo septiembre de 2026: configuración técnica, conformación y capacitación del equipo, transferencia de contexto funcional, y bases de infraestructura y arquitectura (catálogo de eventos, contratos de API, Runtime agéntico y Control Plane). No produce funcionalidad de negocio, pero sin él el Release 1 no arranca.
B7: Release 1 — octubre a diciembre 2026 | C7: El Sprint 1 inicia el 1 de octubre de 2026. La construcción del Release 1 ocupa los sprints 1 a 4 (octubre y noviembre, ~2 meses de trabajo efectivo) y el sprint 5 (7 al 22 de diciembre) queda reservado para estabilización, pruebas y entrega — no para alcance nuevo. El alcance está acotado, según el acuerdo de la sesión del 18-ago, a radicar una solicitud de autorización por un rol y un canal específicos: se excluyen modificaciones, reestudio, anulación, renovación, certificados, exterior, recién nacido e integralidad.
B8: Cómo se acotó el Release 1 | C8: El alcance no se recortó a ojo. Se filtraron los requisitos de Solicitud y Plataforma que pertenecen al camino de radicación, se ordenaron por prioridad MoSCoW y se fueron admitiendo hasta agotar un presupuesto de capacidad: 8 carriles (5 de Solicitud + 3 de Plataforma) x 33 días hábiles de construcción, con 20% de holgura = 211 días hábiles. Entraron 20 requisitos que suman 209 días. Todo lo que no cupo quedó marcado en el backlog como 'Diferido al Release 2 por capacidad del MVP de diciembre', para que la decisión sea visible y reversible.
B9: Por qué el Release 1 es Solicitud y no Evaluación | C9: El equipo confirmó que la dependencia entre gestores sigue el orden del flujo: sin la solicitud ningún otro gestor tiene insumo para operar. Evaluación es el gestor más complejo (pertinencia médica) y su propio mínimo viable tomaría cerca de cuatro meses, por lo que no es viable para diciembre. Solicitud tiene terreno ganado por la reutilización de Siniestro Integral, de un lector de IA existente y de los canales actuales.
B10: Calendario | C10: 100% hábil de Colombia: se excluyen sábados, domingos y los 18 festivos oficiales (incluida Semana Santa, calculados por año con la Ley Emiliani).
B11: Sprints | C11: Sprints de 11 días hábiles. Sprint 0 = todo septiembre de 2026. Sprint 1 = primer día hábil de octubre de 2026.
B12: Escala de talla | C12: XXL = 30 días hábiles (3+ sprints) · XL = 20 días (2 sprints) · L = 10 días (1 sprint) · M = 5 días (medio sprint) · S = 3 días (un cuarto de sprint) · XS = 1 día.
B13: Cómo se asignó la talla | C13: Heurística por palabras clave (arquitectura, motor, IA, integración, catálogo, etc.) más longitud del texto del requisito. Es una primera pasada reproducible, no un tallaje de equipo. La sesión del 18-ago dejó explícito que estas estimaciones preliminares están sujetas a sesgo y deben validarse con el equipo técnico; el ejercicio de dimensionamiento de agentes con el driver de NTT Data es el mecanismo acordado para hacerlo.
B14: Cómo se calcularon las fechas | C14: Cada squad tiene un número de carriles paralelos (aprox. su número de desarrolladores). Los requisitos de cada combinación squad + release se reparten entre esos carriles y cada carril avanza de forma continua según la duración de talla. Ver hoja 'Equipos y Paralelización'.
B15: Celdas en ámbar y verde | C15: Ámbar = dato PENDIENTE POR CONFIRMAR, no completado con supuestos. Verde = definición nueva proveniente de las sesiones del 18 al 20 de agosto de 2026.
B16: Advertencia de contexto | C16: La contingencia del terremoto generó atraso: al 20-ago el avance de estructuración era del 49% frente a un 68% esperado. Estas fechas asumen que el equipo técnico puede arrancar el Sprint 0 el 1 de septiembre.
B18: Ventanas de release (calculadas a partir de la programación real)
B19: Release | C19: Fecha inicio | D19: Fecha fin | E19: Sprints
B20: Sprint 0 | C20: 01-Sep-2026 | D20: 28-Sep-2026 | E20: S0–S0
B21: Release 1 | C21: 01-Oct-2026 | D21: 30-Nov-2026 | E21: S1–S4
B22: Release 2 | C22: 12-Jan-2027 | D22: 08-Jun-2027 | E22: S7–S16
B23: Release 3 | C23: 20-May-2027 | D23: 24-Sep-2027 | E23: S15–S22
B24: Fase posterior | C24: 13-Sep-2027 | D24: 31-Dec-2027 | E24: S22–S28
B27: Elaborado por | C27: Equipo de Estructuración — Proyecto Gestores · Agosto 2026

Sheet Definición-ImpactMap
A1: PLAN DE RELEASES E IMPACT MAP ¿Porqué construimos esto y a quién impacta?
A2: Cada fila es un requisito funcional (RF) o no funcional (RNF) convertido en actividad de release, con su gestor, talla y sprint estimado. Incluye los requisitos del archivo v2 y las definiciones nuevas de las sesiones del 18 al 20 de agosto (columna Origen, resaltada en verde). El Mapa de Actores lista los aplicativos impactados por el Release 1, según instrucción de la plantilla.
A4: PLAN DE RELEASES | L4: MAPA DE ACTORES (solo Release 1)
A5: Release | B5: Gestor(es) asociado(s) | C5: Tipo | D5: Origen | E5: Actividad o Proceso (requisito) | F5: Entregable / Decisión de seguimiento | G5: Categoría de priorización | H5: Talla | I5: Sprint(s) estimado(s) | J5: Observaciones (duda / estado de origen) | L5: Aplicativo | M5: Dominio | N5: Líder TI | O5: Responsable de negocio (APM) | P5: Observaciones
A6: Sprint 0 | B6: Canales / Front Externos | C6: RNF | D6: Sprint 0 (definido 18–20 ago) | E6: Confirmación del alcance del Release 1 con negocio y con el equipo de canales: rol y canal específicos, y compatibilidad de cronogramas. | F6: Por definir en el taller de estimación | G6: Debe tener | H6: M | I6: Sprint 0 | J6: Estado de origen: Sprint 0 — Preparación · Nota: James no había entregado su estimación de esfuerzo al 18-ago. | L6: Sucursal Virtual Prestador de salud y Proveedor de asistencia | M6: Transformación Digital | N6: Juan Carlos Betancur Piedrahita | O6: Lucrecia Andrea Lenis Tangarife; Manuela Molina Ospina | P6: Canal principal del prestador (70–80% del volumen)
A7: Sprint 0 | B7: Transversal / Principios generales | C7: RNF | D7: Sprint 0 (definido 18–20 ago) | E7: Conformación y onboarding del equipo: definición de squads, roles y dedicaciones, y capacitación del personal nuevo en el dominio de autorizaciones de salud. | F7: Riesgo señalado en la sesión del 18-ago | G7: Debe tener | H7: M | I7: Sprint 0 | J7: Estado de origen: Sprint 0 — Preparación · Nota: Armar y capacitar un equipo nuevo puede tomar más de la mitad de septiembre. | L7: Sucursal virtual prestadores (En Desarrollo) | M7: PENDIENTE POR CONFIRMAR | N7: PENDIENTE POR CONFIRMAR | O7: PENDIENTE POR CONFIRMAR | P7: Nuevo portal en construcción; confirmar registro APM
A8: Sprint 0 | B8: Transversal / Principios generales | C8: RNF | D8: Sprint 0 (definido 18–20 ago) | E8: Habilitación de ambientes de desarrollo y pruebas, infraestructura base, repositorios, pipelines de CI/CD y estándares de código. | F8: Por definir en el taller de estimación | G8: Debe tener | H8: M | I8: Sprint 0 | J8: Estado de origen: Sprint 0 — Preparación | L8: Sucursal Virtual Personas | M8: Transformación Digital | N8: Juan Carlos Betancur Piedrahita | O8: Laura Mejía Arango | P8: Front nuevo en Flutter embebido; salida del embebido de ADR
A9: Sprint 0 | B9: Transversal / Principios generales | C9: RNF | D9: Sprint 0 (definido 18–20 ago) | E9: Configuración del Runtime agéntico y del Control Plane corporativo (gateway de consumo de LLM y gestión de prompts) para el equipo de Gestores. | F9: Por definir en el taller de estimación | G9: Debe tener | H9: L | I9: Sprint 0 | J9: Estado de origen: Sprint 0 — Preparación · Nota: Depende del avance de la plataforma agéntica corporativa que construye el equipo de IA. | L9: SuperAPP | M9: Plataforma Digital SURA | N9: Sergio Andrés Pérez Pérez | O9: Erika Andrea Solórzano López | P9: Riesgo técnico abierto: Super App en Google Cloud vs. resto del ecosistema en Azure
A10: Sprint 0 | B10: Transversal / Principios generales | C10: RNF | D10: Sprint 0 (definido 18–20 ago) | E10: Elaboración del borrador del catálogo de eventos y de los contratos de API que servirán de base al Release 1. | F10: Camino crítico: sin este contrato ningún squad puede construir | G10: Debe tener | H10: L | I10: Sprint 0 | J10: Estado de origen: Sprint 0 — Preparación | L10: ADR | M10: Aseguramiento | N10: Alexis De Jesús Ramos Behaine | O10: Camilo Andrés Muñoz Uribe; Carolina Villegas Londoño | P10: Uno de los cuatro sistemas que hoy usa el evaluador en paralelo
A11: Sprint 0 | B11: Transversal / Principios generales | C11: RNF | D11: Sprint 0 (definido 18–20 ago) | E11: Acuerdo formal de capacidad y disponibilidad con el equipo de SuraHis para la exposición de APIs y eventos del core. | F11: Requiere compromiso explícito con Andrés Charry | G11: Debe tener | H11: L | I11: Sprint 0 | J11: Estado de origen: Sprint 0 — Preparación · Nota: Dependencia crítica número uno del proyecto. | L11: Globalweb | M11: Aseguramiento | N11: Alexis De Jesús Ramos Behaine; Germán Darío Tamayo Zuluaga | O11: Sandra Liliana Aristizábal Escobar | P11: Se decide comprobar derechos vía SuraHis y no vía Global Web
A12: Sprint 0 | B12: Transversal / Principios generales | C12: RNF | D12: Sprint 0 (definido 18–20 ago) | E12: Transferencia de contexto funcional al equipo técnico: proceso actual de autorizaciones, modelo de estados, entidades y decisiones de arquitectura ya tomadas. | F12: Por definir en el taller de estimación | G12: Debe tener | H12: L | I12: Sprint 0 | J12: Estado de origen: Sprint 0 — Preparación | L12: Siniestro integral | M12: Aseguramiento | N12: Alexis De Jesús Ramos Behaine | O12: osiris Acevedo Blanco | P12: Base reutilizada (front, back, API Gateway, orquestador, storage)
A13: Sprint 0 | B13: Transversal / Principios generales | C13: RNF | D13: Sprint 0 (definido 18–20 ago) | E13: Cierre del ejercicio de dimensionamiento de agentes y estimación de costo, aplicando el driver construido con NTT Data. | F13: Ejercicio iniciado el 21-ago de 1:30 p.m. a 5:00 p.m. | G13: Debe tener | H13: M | I13: Sprint 0 | J13: Estado de origen: Sprint 0 — Preparación · Nota: El driver estaba en borrador al 20-ago. | L13: Apigee | M13: Plataforma Digital SURA | N13: Sergio Andrés Pérez Pérez | O13: Carlos David Arango Castaño | P13: Exposición API First y MCP hacia canales, aliados y agentes
A14: Sprint 0 | B14: Transversal / Principios generales | C14: RNF | D14: Sprint 0 (definido 18–20 ago) | E14: Definición del umbral de asertividad y de las métricas de calidad de los agentes que se aplicarán desde el Release 1. | F14: Por definir en el taller de estimación | G14: Debe tener | H14: M | I14: Sprint 0 | J14: Estado de origen: Sprint 0 — Preparación · Nota: Valor exacto del umbral por definir. | L14: HIS Administrativo Salud (SuraHis) | M14: Prestación / Distribución | N14: Andrés Felipe Charry Correa | O14: Paula Andrea Peña Sierra | P14: Dependencia crítica: fuente de verdad transaccional, no motor de reglas
A15: Sprint 0 | B15: Transversal / Principios generales | C15: RNF | D15: Sprint 0 (definido 18–20 ago) | E15: Validación con el equipo técnico de los tallajes y estimaciones preliminares, y ajuste del backlog del Release 1 antes de iniciar la implementación. | F15: Por definir en el taller de estimación | G15: Debe tener | H15: M | I15: Sprint 0 | J15: Estado de origen: Sprint 0 — Preparación | L15: P8 (Archivo Digital) | M15: Servicios de infraestructura de TI | N15: José Alejandro Betancur Mejía; Daniel Stiven Ruiz Díaz | O15: Daniel Stiven Ruiz Díaz | P15: Dependencia crítica para custodia documental; PoC con Oracle como alternativa
A16: Sprint 0 | B16: Gestor de Solicitud | C16: RNF | D16: Sprint 0 (definido 18–20 ago) | E16: Decisión técnica del lector de IA a reutilizar (ADR vs. desarrollo de TT) y prueba de concepto de la extracción documental sobre documentos reales. | F16: Por definir en el taller de estimación | G16: Debe tener | H16: L | I16: Sprint 0 | J16: Estado de origen: Sprint 0 — Preparación · Nota: Impactada por el recorte de presupuesto del equipo de salud modular. | L16: Notificaciones | M16: Soluciones Corporativas | N16: Daniel Stiven Ruiz Díaz | O16: Daniel Stiven Ruiz Díaz | P16: Notificación proactiva basada en eventos
... A22: Release 1 | B22: Transversal / Principios generales | C22: RNF | D22: Sesión 18-ago | E22: Confirmar el orden de dependencia entre gestores: cada gestor requiere el evento o salida del anterior, por lo que el Gestor de Solicitud es el punto de partida obligado del flujo. | F22: Sin la solicitud ningún otro gestor tiene insumo para operar | G22: Debe tener | H22: L | I22: S3–S4 | J22: Estado de origen: Nuevo — Definido en sesión 18-ago | L22: KONECTA (contact center) | M22: Actor externo — no aplicativo APM | N22: PENDIENTE POR CONFIRMAR | O22: PENDIENTE POR CONFIRMAR | P22: Link de gestión con hallazgos de seguridad; impacto contractual por reducción de preradicación
A23: Release 1 | B23: Gestor de Solicitud | C23: RF | D23: Requisitos v2 (12-ago) | E23: Documento no legible nunca bloquea al usuario: siempre pasa a bandeja de revisión manual. | F23: Por definir en el taller de estimación | G23: Debe tener | H23: M | I23: S1 | J23: Estado de origen: Definido
A24: Release 1 | B24: Siniestro Integral | C24: RF | D24: Requisitos v2 (12-ago) | E24: Modelo de datos "padre-hijo": la solicitud es el padre; cada autorización por servicio/CUPS es un hijo con estado propio. | F24: Por definir en el taller de estimación | G24: Debe tener | H24: M | I24: S1 | J24: Estado de origen: Definido
A25: Release 1 | B25: Gestor de Solicitud | C25: RF | D25: Requisitos v2 (12-ago) | E25: Extrae mediante agente IA la información de los documentos adjuntos (orden médica + historia clínica). | F25: Por definir en el taller de estimación | G25: Debe tener | H25: L | I25: S1 | J25: Estado de origen: Definido
A26: Release 1 | B26: Siniestro Integral | C26: RF | D26: Requisitos v2 (12-ago) | E26: Genera un ID temporal como número radicador (correlation ID), y almacena la información de forma temporal. | F26: Por definir en el taller de estimación | G26: Debe tener | H26: S | I26: S1 | J26: Estado de origen: Definido
A27: Release 1 | B27: Siniestro Integral | C27: RF | D27: Requisitos v2 (12-ago) | E27: Lleva los documentos a P8. | F27: Por definir en el taller de estimación | G27: Debe tener | H27: XS | I27: S1 | J27: Estado de origen: Definido
A28: Release 1 | B28: Siniestro Integral | C28: RF | D28: Requisitos v2 (12-ago) | E28: Publica el evento que activa al core de salud (SuraHis) para la generación de la solicitud; ese mismo evento alimenta el flujo de solicitud/autorización para la Torre de Control. | F28: Por definir en el taller de estimación | G28: Debe tener | H28: M | I28: S1 | J28: Estado de origen: Definido
A29: Release 1 | B29: Gestor de Solicitud | C29: RF | D29: Requisitos v2 (12-ago) | E29: Si la IA no identifica el documento con certeza, el caso va a bandeja manual sin notificar al asegurado que el documento es inválido (evita falsos negativos); solo se notifica si hay certeza de que el documento no corresponde. | F29: Por definir en el taller de estimación | G29: Debe tener | H29: XXL | I29: S1–S3 | J29: Estado de origen: Definido en sesión 10-ago
A30: Release 1 | B30: Gestor de Solicitud | C30: RF | D30: Requisitos v2 (12-ago) | E30: La bandeja de solicitud incompleta tiene bloqueo por exclusión mutua (mutex) mientras un analista/agente la trabaja, y un tiempo de vida (TTL) tras el cual se libera y puede escalarse. | F30: Por validar con negocio (ver hoja de Pendientes y Conversaciones) | G30: Debe tener | H30: L | I30: S1–S2 | J30: Estado de origen: Nuevo — Definido en sesión técnica 12-ago · Nota: Falta definir con negocio el valor exacto del TTL y el criterio de escalamiento por tipo de caso.
A31: Release 1 | B31: Gestor de Solicitud | C31: RNF | D31: Requisitos v2 (12-ago) | E31: Front nuevo (Flutter), embebido en Sucursal Virtual Personas, AVA y Portal de Prestadores; reutiliza el back/orquestador de Siniestro Integral. | F31: Por definir en el taller de estimación | G31: Debe tener | H31: M | I31: S1 | J31: Estado de origen: Definido
A32: Release 1 | B32: Gestor de Solicitud | C32: RNF | D32: Requisitos v2 (12-ago) | E32: Comprobación de derechos vía API de SuraHis (no Global Web) — mayor resiliencia y flexibilidad ante cambios futuros de core. | F32: Por definir en el taller de estimación | G32: Debe tener | H32: M | I32: S1 | J32: Estado de origen: Definido
A33: Release 1 | B33: Gestor de Solicitud | C33: RNF | D33: Requisitos v2 (12-ago) | E33: OCR/IA: LLM multimodal interpreta documentos directamente (15-40 seg); reutiliza el agente de pre-radicación de EPS (~93% de precisión). | F33: Por definir en el taller de estimación | G33: Debe tener | H33: L | I33: S1–S2 | J33: Estado de origen: Definido
A34: Release 1 | B34: Gestor de Solicitud | C34: RNF | D34: Requisitos v2 (12-ago) | E34: Arquitectura orientada a eventos: quien tiene autoridad sobre la entidad (normalmente SuraHis) es quien emite el evento. | F34: Por definir en el taller de estimación | G34: Debe tener | H34: XL | I34: S1–S3 | J34: Estado de origen: Definido
... A183: Fase posterior | B183: Gestor de Prestación | C183: RNF | D183: Requisitos v2 (12-ago) | E183: Integración con la cola de eventos de interoperabilidad de historia clínica (arquitectura 2.0) para conocer si el servicio autorizado fue efectivamente atendido, sin construir un componente tecnológico nuevo en Gestores. | F183: Por definir en el taller de estimación | G183: No debería | H183: XXL | I183: S26–S28 | J183: Estado de origen: Nuevo — Definido en sesión de Interoperabilidad 11-ago
A185: Leyenda | D185: Talla:
A186: Sprint 0 · sep-2026 (preparación) | D186: XS · 1 día
A187: Release 1 · oct–dic 2026 | D187: S · 3 días · 1/4 sprint
A188: Release 2 | D188: M · 5 días · 1/2 sprint
A189: Release 3 | D189: L · 10 días · 1 sprint
A190: Fase posterior / fuera de MVP | D190: XL · 20 días · 2 sprints
A191: Pendiente por confirmar | D191: XXL · 30 días · 3+ sprints

Sheet Estimación-Visual Story Map
A1: FASE DE ESTIMACIÓN · VISUAL STORY MAP — ¿Qué entra en cada release?
A2: Épicas = squads (gestores agrupados). Cada 'feature' agrupa hasta 6 requisitos en el orden del archivo fuente. El color de cada celda indica el release; el código entre corchetes es la talla del requisito.
A4: ÉPICAS | C4: Plataforma (Sprint 0) | I4: Solicitud (Sprint 0) | Q4: Canales (Sprint 0) | U4: Evaluación (Release 2) | AA4: Coordinación (Release 3) | AF4: Torre de Control (Release 3) | AL4: Prestación (Fase posterior) | AO4: Finalización (Fase posterior)
A5: FEATURES | C5: Bloque 1 Conformación y onboarding del… | D5: Bloque 2 Cierre del ejercicio de… | E5: Bloque 3 Riesgo/premisa explícita: el proyecto… | F5: Bloque 4 La interoperabilidad de historia… | G5: Bloque 5 Versionamiento de sistemas agénticos,… | I5: Bloque 1 Decisión técnica del lector… | J5: Bloque 2 Publica el evento que… | K5: Bloque 3 Arquitectura orientada a eventos:… | L5: Bloque 4 Se incorpora como requisito… | M5: Bloque 5 Modelo de datos de… | N5: Bloque 6 Modelo asíncrono de bandeja… | O5: Bloque 7 Umbral de asertividad: cada… | Q5: Bloque 1 Confirmación del alcance del… | R5: Bloque 2 Selección de prestador: el… | S5: Bloque 3 'Solicitar estado de cuenta'… | U5: Bloque 1 Consulta al Core (SuraHis)… | V5: Bloque 2 No genera el número… | W5: Bloque 3 Principio de diseño: la… | X5: Bloque 4 Evaluación estructurada en dos… | Y5: Bloque 5 La solicitud de autorización… | AA5: Bloque 1 La asignación al equipo… | AB5: Bloque 2 La notificación al cliente… | AC5: Bloque 3 Notifica tanto al asegurado… | AD5: Bloque 4 Integración con prestadores externos… | AF5: Bloque 1 Renombrado de "Monitoreo" a… | AG5: Bloque 2 Rescate digital automático: si… | AH5: Bloque 3 Arquitectura orientada a eventos… | AI5: Bloque 4 Controlar los niveles de… | AJ5: Bloque 5 El Data Lake es… | AL5: Bloque 1 Da seguimiento al "momento… | AM5: Bloque 2 Integración con clave dinámica… | AO5: Bloque 1 Es el gestor menos… | AP5: Bloque 2 Excluye explícitamente las "reglas…
A6: Req. 1 | C6: [M] Conformación y onboarding del equipo: definición de squads, roles y dedicaciones, y capacitació… | D6: [M] Cierre del ejercicio de dimensionamiento de agentes y estimación de costo, aplicando el driver … | E6: [M] Riesgo/premisa explícita: el proyecto solo tiene sentido si los cores implementan la capacidad … | F6: [XXL] La interoperabilidad de historia clínica ya cuenta con una arquitectura 2.0 orientada a eventos… | G6: [L] Versionamiento de sistemas agénticos, incluyendo la definición de si la data de reglas del core… | I6: [L] Decisión técnica del lector de IA a reutilizar (ADR vs. desarrollo de TT) y prueba de concepto … | J6: [M] Publica el evento que activa al core de salud (SuraHis) para la generación de la solicitud; ese… | K6: [XL] Arquitectura orientada a eventos: quien tiene autoridad sobre la entidad (normalmente SuraHis) … | L6: [S] Se incorpora como requisito funcional el "rescate de la solicitud" cuando la radicación no se c… | M6: [XL] Modelo de datos de la bandeja de solicitud: entidad flexible con campos por defecto 'desconocid… | N6: [XL] Modelo asíncrono de bandeja de solicitudes (recibida / notificación cuando requiere atención) e… | O6: [M] Umbral de asertividad: cada campo extraído viene con un porcentaje de confianza. Solo por encim… | Q6: [M] Confirmación del alcance del Release 1 con negocio y con el equipo de canales: rol y canal espe… | R6: [S] Selección de prestador: el campo queda como opcional y se traslada a un paso posterior del fluj… | S6: [L] 'Solicitar estado de cuenta' se renombra de cara al usuario (los asegurados lo conocen como 'ce… | U6: [M] Consulta al Core (SuraHis) coberturas, vigencias, convenios y exclusiones para los controles de… | V6: [M] No genera el número de solicitud de autorización/negación: deja el caso listo vía evento — el c… | W6: [L] Principio de diseño: la negación siempre debe ser determinística y trazable — nunca una decisió… | X6: [XXL] Evaluación estructurada en dos llamados al core en paralelo: reglas duras (producto, diagnóstic… | Y6: [M] La solicitud de autorización se desglosa en autorizaciones asociadas a un solo servicio, no a n… | AA6: [L] La asignación al equipo se distribuye según reglas de criticidad (marcas en salud, PEP, edad de… | AB6: [M] La notificación al cliente por incumplimiento de SLA se dispara vía evento publicado por la Tor… | AC6: [S] Notifica tanto al asegurado (prestador asignado) como al prestador (autorización pendiente de a… | AD6: [L] Integración con prestadores externos preferiblemente vía API con retroalimentación de estados. | AF6: [XS] Renombrado de "Monitoreo" a "Torre de Control" por ampliación de alcance durante las sesiones. | AG6: [L] Rescate digital automático: si falla el canal al radicar, contacta por WhatsApp/app para contin… | AH6: [XL] Arquitectura orientada a eventos (EDA): consume eventos de todos los gestores y cores, incluida… | AI6: [XS] Controlar los niveles de autonomía de los gestores agénticos. | AJ6: [M] El Data Lake es una fuente más de información para la Torre de Control (solo lectura, no consum… | AL6: [M] Da seguimiento al "momento de verdad": si la cita fue programada, si el paciente asistió, noved… | AM6: [XL] Integración con clave dinámica (doble factor) como mecanismo de confirmación de la atención efe… | AO6: [S] Es el gestor menos desarrollado de los 6 — solo definición conceptual, sin sesión de estructura… | AP6: [M] Excluye explícitamente las "reglas de pago automático" (corresponden a Cuentas Médicas, fuera d…
A7: Req. 2 | C7: [M] Habilitación de ambientes de desarrollo y pruebas, infraestructura base, repositorios, pipeline… | D7: [M] Definición del umbral de asertividad y de las métricas de calidad de los agentes que se aplicar… | E7: [XL] Se reutiliza la arquitectura de "Siniestro Integral" (Front + Back, API Gateway, orquestador, s… | F7: [M] Adoptar la metodología de estimar por cada gestor un escenario mínimo viable y uno completo/des… | G7: [L] Concepto de 'function fitness': pruebas equivalentes a las de desarrollo de software aplicadas … | I7: [M] Documento no legible nunca bloquea al usuario: siempre pasa a bandeja de revisión manual. | J7: [XXL] Si la IA no identifica el documento con certeza, el caso va a bandeja manual sin notificar al a… | K7: [S] Recibe solicitudes de 3 públicos: prestador (70-80% del volumen, foco prioritario), cliente/ase… | L7: [S] Modelo de 'solicitud laxa': la solicitud se crea con campos comodín (valores 'desconocido') que… | M7: [M] Alcance acotado del primer entregable de diciembre: radicar una solicitud de autorización para … | N7: [S] Alertar al asegurado cuando el documento cargado no corresponde a lo esperado, sin afectar su e… | O7: [S] Mecanismo de muestreo humano sobre los casos que el agente resuelve correctamente, no solo sobr… | Q7: [M] Comprobación de derechos (vigencia de póliza, mora) obligatoria al inicio del flujo, antes de p… | R7: [M] Reestudio: aplica solo cuando la autorización fue negada y el asegurado no está de acuerdo; el … | S7: [M] Reutilizar los canales existentes hoy para el primer release, coordinando en paralelo la estima… | U7: [M] Valida la pertinencia médica; decide autorizar, negar o escalar a evaluación manual (coherencia… | V7: [XL] Reutiliza el homologador de CUPS y el motor ya productivo del proyecto de autorizaciones EPS, e… | W7: [M] Hoy el evaluador humano usa 4 sistemas en paralelo (ADP, Global Web, ADR, P8) — meta explícita:… | X7: [L] La bandeja de 'listo para coordinación' tras una evaluación exitosa es la misma bandeja de 'pag… | Y7: [L] Si un servicio no se puede autorizar por la póliza voluntaria, esa solicitud hijo se niega y se… | AA7: [M] Para solicitudes pendientes por gestión se habilita la reasignación entre niveles. | AB7: [M] Direcciona el servicio ya autorizado al prestador adecuado: simple (un solo prestador posible, … | AC7: [S] Objetivo estratégico: mapear automáticamente la autorización contra el convenio/tarifa para pag… | AD7: [XL] Bandeja "human in the loop" para casos donde ni las reglas ni la recomendación logran asignar u… | AF7: [S] Monitorea el ciclo de vida completo de la autorización: cumplimiento de SLA/ANS, carga de traba… | AG7: [S] Detecta solicitudes repetidas (2 o más veces) con las mismas características y activa el mismo … | AH7: [M] El almacenamiento de eventos vive en un bus/componente dedicado, no exclusivo de este gestor — … | AI7: [M] Entregar información a distintos canales en el lenguaje requerido por cada actor, registrando c… | AJ7: [XL] Arquitectura tipo Lambda: vía rápida de eventos en tiempo real más vía lenta de productos del D… | AL7: [M] Mecanismo actual: confirmación por QR escaneado por el asegurado (piloto ya finalizado, solo co… | AM7: [L] Sin arquitectura técnica profundizada — reconocido explícitamente por el equipo de arquitectura… | AO7: [S] 3 pilares: satisfacción del cliente · conciliación y pago a proveedor (cuentas médicas) · pagos… | AP7: [L] Sin arquitectura ni componentes técnicos definidos en ninguna de las fuentes revisadas a la fec…
A8: Req. 3 | C8: [L] Configuración del Runtime agéntico y del Control Plane corporativo (gateway de consumo de LLM y… | D8: [M] Validación con el equipo técnico de los tallajes y estimaciones preliminares, y ajuste del back… | E8: [M] Se privilegia un front único reutilizable por canal/actor, en lugar de un front independiente p… | F8: [XL] Plataforma agéntica corporativa en construcción con el equipo de IA: Runtime agéntico (donde co… | G8: [M] Driver de dimensionamiento de agentes: parametrizar la complejidad de cada agente para aproxima… | I8: [M] Modelo de datos "padre-hijo": la solicitud es el padre; cada autorización por servicio/CUPS es … | J8: [L] La bandeja de solicitud incompleta tiene bloqueo por exclusión mutua (mutex) mientras un analis… | K8: [S] Meta: pedir solo identificación (aplica solo para prestador y asesor) + 2 documentos (historia … | L8: [L] Flujo: Front → Storage temporal de documentos → integración asíncrona con P8; PoC en curso con … | M8: [XL] Reutilizar el componente de Siniestro Integral a nivel de back para el primer release, en lugar… | N8: [M] Capa de agentes expertos: un agente por tipo de documento (historia clínica, orden médica, fact… | O8: [M] Límite de auto-reparación de prompts del agente auditor: no puede ser totalmente autónomo sin a… | Q8: [L] Documentos aparentemente inválidos no permiten continuar con la creación de la solicitud (agent… | R8: [M] Notificación y visibilidad cruzada cliente-prestador: se notifica al cliente cuando un prestado… | U8: [S] Regla crítica: la negación nunca se hace 100% automática — toda negación exige intervención de … | V8: [XL] Valida duplicidad (mismo prestador/documentos o mismo tipo de servicio) consultando histórico e… | W8: [M] Es, junto con Solicitud, el gestor con mayor avance de diseño a la fecha del último seguimiento… | X8: [M] Auditoría de decisiones automáticas: detectar desviaciones estadísticas y realizar revisión man… | AA8: [S] Cada solicitud debe tener un tiempo de respuesta asignado (100% de las solicitudes en menos de … | AB8: [M] 3 casos de negocio: producto modular (direccionamiento automático) · clásica/global (cliente el… | AC8: [L] Para el Release 1, la asignación interna de casos a evaluadores/niveles la resuelve SuraHis; el… | AD8: [M] Es uno de los gestores menos profundizados técnicamente a la fecha — "no se ha hecho zoom" toda… | AF8: [S] Regla explícita: no se monitorea todo lo que llega, solo lo que "se sale de lo esperado" — la c… | AG8: [M] Notificaciones basadas en eventos: el Core informa tiempos por etapa, la Torre de Control detec… | AH8: [L] Pendiente definir si se expone una API única con filtrado por perfil o múltiples APIs por actor… | AI8: [S] Detección de anomalías y fraude como capacidad agéntica, aprovechando la vista panorámica que e… | AJ8: [M] La capa de ingesta y consolidación debe tener capacidad de streaming, no procesamiento por lote… | AL8: [L] Se evalúa evolucionar a clave dinámica (doble factor, ya disponible en la app) como mecanismo d… | AM8: [XXL] Integración con la cola de eventos de interoperabilidad de historia clínica (arquitectura 2.0) … | AO8: [M] Equivale, en autorizaciones, al pago de la cuenta médica: el prestador carga la factura con det… | AP8: [XL] El Gestor de Finalización se representa en la arquitectura con líneas punteadas: no se implemen…
A9: Req. 4 | C9: [L] Elaboración del borrador del catálogo de eventos y de los contratos de API que servirán de base… | D9: [XL] Arquitectura de microservicios, agéntica, dirigida por eventos (EDA), moderna y desacoplada — s… | E9: [M] Diferenciación explícita comando (síncrono, se consume y desaparece) vs. evento (inmutable, usa… | F9: [L] Distinguir eventos funcionales (de las entidades de negocio, emitidos por su dueño) de eventos … | I9: [L] Extrae mediante agente IA la información de los documentos adjuntos (orden médica + historia cl… | J9: [M] Front nuevo (Flutter), embebido en Sucursal Virtual Personas, AVA y Portal de Prestadores; reut… | K9: [M] Autorización automática (algunas no requieren soportes) en servicios clasificados como "nivel 1… | L9: [L] Integración con NEXO vía API (patrón API First) + exposición como MCP para agentes conversacion… | M9: [XL] Reutilizar un lector de IA existente para la extracción documental: definir si se usa el de ADR… | N9: [M] Capa de salida configurable: arma el resultado final según lo que cada core consumidor necesite… | O9: [M] Agente juez que valide en tiempo real usando un modelo distinto al del agente evaluado, para qu… | Q9: [S] Omnicanalidad real: el historial de solicitudes/autorizaciones debe verse igual sin importar el… | R9: [S] Anulación de solicitudes: solo la puede hacer el prestador, y solo si el estado es 'en proceso'… | U9: [L] Revisar la integración para consultar mora (ir directamente al core de PDN o pasar por SuraHis)… | V9: [M] Consume la información ya extraída y estructurada por el gestor de Solicitud — no relee los doc… | W9: [M] Capa de duplicados determinística, sin componente de IA: aplica reglas de negocio por especiali… | X9: [XL] Gobernanza de reglas: en vez de traer el motor de reglas al gestor, este consume una tool que i… | AA9: [M] Se debe habilitar la opción de solicitud de requisitos (notificar al cliente); al adjuntar el s… | AB9: [M] Criterios de priorización de prestadores: quejas (Medallia), satisfacción, disponibilidad de ci… | AC9: [XL] Arranca con motor 100% determinístico (reglas duras de elegibilidad, convenios, capacidad, ubic… | AD9: [L] Pendiente definir el dueño y el mecanismo de sincronización de las reglas de direccionamiento/c… | AF9: [S] Visión ampliada: capacidades proactivas (contactar directamente al cliente/prestador) y potesta… | AG9: [XS] Notifica al asegurado ante incumplimiento de SLA (mensaje de acompañamiento) y alerta intername… | AH9: [L] Reto de integración en tiempo real con prestadores — hoy no existe (solo portal con interacción… | AI9: [S] Medir KPIs de eficiencia y productividad: tiempo de ciclo promedio, tiempo de espera, tiempo de… | AJ9: [M] La Torre de Control no tendrá un front propio de visualización al usuario final: la visibilidad… | AL9: [XL] Visión ideal (aún no lograda ni por EPS): OTP de asistencia + interoperabilidad directa con el … | AO9: [S] Objetivo: que autorización y tarifa contratada queden tan conectadas que no haya que glosar ni … | AP9: [L] El proceso de conciliación y glosas (conocido en el negocio como 'finiquito') no se considera u…
A10: Req. 5 | C10: [L] Acuerdo formal de capacidad y disponibilidad con el equipo de SuraHis para la exposición de API… | D10: [M] Principio "coreless": la lógica de negocio (reglas, políticas, convenios) se desacopla de los c… | E10: [L] Confirmar el orden de dependencia entre gestores: cada gestor requiere el evento o salida del a… | F10: [L] La Solicitud y la Autorización hacen parte del core (SuraHis), por lo que SuraHis debe garantiz… | I10: [S] Genera un ID temporal como número radicador (correlation ID), y almacena la información de form… | J10: [M] Comprobación de derechos vía API de SuraHis (no Global Web) — mayor resiliencia y flexibilidad … | K10: [M] Integralidad automática con EPS Sura cuando la póliza voluntaria no cubre el servicio y se gene… | L10: [S] Custodia temporal de historia clínica/orden médica en componente propio. | M10: [XL] Definir si el radicado debe quedar garantizado en SuraHis desde el primer release, o si basta c… | N10: [L] No hay rechazo automático: todo lo que el agente no puede resolver pasa a bandeja humana indica… | O10: [L] Validar qué tipos de archivo puede almacenar el repositorio documental de los gestores (si admi… | Q10: [M] No requiere segundo factor de autenticación en el flujo de solicitud desde la app (sí se evalua… | R10: [XL] Solicitud en el exterior: flujo distinto al general — no genera una autorización tradicional; l… | U10: [M] Niveles de escalamiento: Nivel 1 automático · Nivel 2 administrativo · Niveles 3 (enfermeras/in… | V10: [XXL] Debe consultar políticas/reglas a SuraHis manteniendo también reglas propias de agente (modelo … | W10: [M] El gestor no rellena información faltante ni garantiza la completitud de la información: entra … | X10: [L] SuraHis dispone de un módulo parametrizable de reglas duras que permite eliminarlas, modificarl… | AA10: [M] Con la negación de un servicio se debe activar la radicación automática de la solicitud de inte… | AB10: [S] Si el prestador elegido no tiene convenio vigente, se asigna automáticamente el mejor rankeado … | AC10: [L] LLM reservado solo para casos no estructurados o de explicación — no es prioridad para el arran… | AF10: [S] Responsable de detectar comportamiento anómalo de los agentes (ej. ratio de rechazos fuera de l… | AG10: [S] Requiere vista individual (línea de tiempo por solicitud) y vista grupal/masiva (operación agre… | AH10: [L] Datalake de autorizaciones como entregable técnico del Release 3 (feb-abr 2027), con apoyo del … | AI10: [S] Reportar a los líderes de operación cuando un equipo esté saturado o dejando de recibir autoriz… | AJ10: [M] Trazar el límite entre las alertas que resuelve el propio core con un timer (ej. SLA vencido) y… | AL10: [XS] Mecanismo de registro de asistencia en SuraHis. | AO10: [S] El fraude también puede materializarse aquí (sobrefacturación, sobretratamiento) — debe tratars…
A11: Req. 6 | C11: [L] Transferencia de contexto funcional al equipo técnico: proceso actual de autorizaciones, modelo… | D11: [XXL] El core (SuraHis) debe ser la fuente de la verdad transaccional, no el motor de reglas — princi… | E11: [S] Cada gestor tendría base de datos propia, independiente y desacoplada. | F11: [M] Marco de buenas prácticas para sistemas agénticos: criterios de asertividad y trazabilidad para… | I11: [XS] Lleva los documentos a P8. | J11: [L] OCR/IA: LLM multimodal interpreta documentos directamente (15-40 seg); reutiliza el agente de p… | K11: [S] Nueva funcionalidad "Reestudio": permite pedir reevaluación de una solicitud negada adjuntando … | L11: [S] Riesgo técnico abierto: Super App en Google Cloud vs. resto del ecosistema en Azure. | M11: [M] El agente receptor no asume que los archivos llegan bien identificados ni separados: debe detec… | N11: [M] Capa de auditoría: analiza el histórico de solicitudes y reporta patrones a la Torre de Control… | O11: [L] Flujo de activación confirmado: el Front informa a Siniestro Integral, este guarda la informaci… | Q11: [M] Front con/sin documentos dependiendo del tipo de servicio de cara al prestador; front con docum… | R11: [M] Caso especial de inclusión de recién nacido para atención urgente: flujo corto e independiente,… | U11: [L] El agente entrega un "concepto"/resumen de su análisis al escalar a la bandeja manual, para ace… | V11: [XXL] Arquitectura híbrida multiagente propuesta: agente determinístico (coberturas/exclusiones) + ag… | W11: [L] Si durante la evaluación falta un dato que no era obligatorio en la solicitud pero sí es necesa… | X11: [M] El Gestor de Evaluación no es transversal: está diseñado específicamente para autorizaciones de… | AA11: [S] Se debe habilitar la opción de resignación manual de solicitudes a otro evaluador (novedades co… | AB11: [L] Si no hay red contratada en la ciudad, se recomienda la ciudad más cercana o se escala a Conven… | AC11: [M] Niveles de madurez agéntica: Nivel 1 determinístico → Nivel 2 + asistente explicativo → Nivel 3… | AF11: [M] Expone información distinta según el actor consultante (prestador, cliente, asesor), enmascaran… | AG11: [M] La Torre de Control no emite los eventos de cambio de estado (los emite el componente dueño de … | AH11: [XL] Concepto en discusión: 'agente auditor' transversal que retroalimente a los gestores con aprend… | AI11: [S] Detectar cuentas por pagar próximas a vencer y generar alertas, evitando llamadas de prestadore… | AJ11: [L] Nuevas entidades que deben emitir eventos hacia la Torre de Control: cuenta médica, orden de pa… | AL11: [XXL] El gestor de Prestación no se implementa como componente agéntico independiente para el alcance… | AO11: [M] Se propone reutilizar el agente ya existente en EPS que lee/transcribe autorizaciones y valida …
A14: Leyenda de release | D14: RESULTADO
A15: Sprint 0 | D15: Tablero | F15: Azure DevOps
A16: Release 1 | D16: ID de la iniciativa en Azure | F16: PENDIENTE POR CONFIRMAR
A17: Release 2 | D17: URL de la iniciativa en Azure | F17: PENDIENTE POR CONFIRMAR
A18: Release 3 | D18: Total de requisitos mapeados | F18: =COUNTA(Estimación!A6:A243) -> 173
A19: Fase posterior | D19: Actividades en Sprint 0 | F19: =COUNTIF(Estimación!D6:D243,"Sprint 0") -> 11
D20: Requisitos en Release 1 (MVP dic-2026) | F20: =COUNTIF(Estimación!D6:D243,"Release 1") -> 13
D21: Requisitos en Release 2 | F21: =COUNTIF(Estimación!D6:D243,"Release 2") -> 78
D22: Requisitos en Release 3 | F22: =COUNTIF(Estimación!D6:D243,"Release 3") -> 52
D23: Requisitos talla XL/XXL | F23: =COUNTIF(Estimación!H6:H243,"XL")+COUNTIF(Estimación!H6:H243,"XXL") -> 26
D24: Total días hábiles estimados | F24: =SUM(Estimación!I6:I243) -> 1442

Sheet Estimación
A1: BACKLOG DE ESTIMACIÓN — requisitos funcionales y no funcionales con fecha
A2: Sprints de 11 días hábiles, calendario de Colombia (festivos incluidos). Fecha inicio/fin calculada según la talla de cada requisito y el carril del squad que lo atiende (ver hoja 'Equipos y Paralelización'). La talla es una heurística de primera pasada — Estado de refinamiento indica que debe confirmarse en el taller de estimación.
A5: ID | B5: Gestor / Frente | C5: Equipo | D5: Release | E5: Actividad / Requisito | F5: Entregable | G5: Prioridad | H5: Talla | I5: Duración (días hábiles) | J5: Sprint(s) | K5: Fecha inicio | L5: Fecha fin | M5: Dependencia | N5: Seguimiento | O5: Estado de refinamiento
A6: REQ-179 | B6: Canales / Front Externos | C6: Canales | D6: Sprint 0 | E6: Confirmación del alcance del Release 1 con negocio y con el equipo de canales: rol y canal específicos, y compatibilidad de cronogramas. | G6: Debe tener | H6: M | I6: 5 | J6: Sprint 0 | K6: 46266 | L6: 46272 | M6: James no había entregado su estimación de esfuerzo al 18-ago. | N6: — | O6: Por confirmar talla
A7: REQ-170 | B7: Transversal / Principios generales | C7: Plataforma | D7: Sprint 0 | E7: Conformación y onboarding del equipo: definición de squads, roles y dedicaciones, y capacitación del personal nuevo en el dominio de autorizaciones de salud. | G7: Debe tener | H7: M | I7: 5 | J7: Sprint 0 | K7: 46266 | L7: 46272 | M7: Armar y capacitar un equipo nuevo puede tomar más de la mitad de septiembre. | N7: Riesgo señalado en la sesión del 18-ago | O7: Por confirmar talla
A8: REQ-171 | B8: Transversal / Principios generales | C8: Plataforma | D8: Sprint 0 | E8: Habilitación de ambientes de desarrollo y pruebas, infraestructura base, repositorios, pipelines de CI/CD y estándares de código. | G8: Debe tener | H8: M | I8: 5 | J8: Sprint 0 | K8: 46266 | L8: 46272 | M8: — | N8: — | O8: Por confirmar talla
A9: REQ-172 | B9: Transversal / Principios generales | C9: Plataforma | D9: Sprint 0 | E9: Configuración del Runtime agéntico y del Control Plane corporativo (gateway de consumo de LLM y gestión de prompts) para el equipo de Gestores. | G9: Debe tener | H9: L | I9: 10 | J9: Sprint 0 | K9: 46266 | L9: 46279 | M9: Depende del avance de la plataforma agéntica corporativa que construye el equipo de IA. | N9: — | O9: Por confirmar talla
A10: REQ-173 | B10: Transversal / Principios generales | C10: Plataforma | D10: Sprint 0 | E10: Elaboración del borrador del catálogo de eventos y de los contratos de API que servirán de base al Release 1. | G10: Debe tener | H10: L | I10: 10 | J10: Sprint 0 | K10: 46266 | L10: 46279 | M10: — | N10: Camino crítico: sin este contrato ningún squad puede construir | O10: Por confirmar talla
A11: REQ-174 | B11: Transversal / Principios generales | C11: Plataforma | D11: Sprint 0 | E11: Acuerdo formal de capacidad y disponibilidad con el equipo de SuraHis para la exposición de APIs y eventos del core. | G11: Debe tener | H11: L | I11: 10 | J11: Sprint 0 | K11: 46273 | L11: 46286 | M11: Dependencia crítica número uno del proyecto. | N11: Requiere compromiso explícito con Andrés Charry | O11: Por confirmar talla
A12: REQ-175 | B12: Transversal / Principios generales | C12: Plataforma | D12: Sprint 0 | E12: Transferencia de contexto funcional al equipo técnico: proceso actual de autorizaciones, modelo de estados, entidades y decisiones de arquitectura ya tomadas. | G12: Debe tener | H12: L | I12: 10 | J12: Sprint 0 | K12: 46273 | L12: 46286 | M12: — | N12: — | O12: Por confirmar talla
A13: REQ-176 | B13: Transversal / Principios generales | C13: Plataforma | D13: Sprint 0 | E13: Cierre del ejercicio de dimensionamiento de agentes y estimación de costo, aplicando el driver construido con NTT Data. | G13: Debe tener | H13: M | I13: 5 | J13: Sprint 0 | K13: 46280 | L13: 46286 | M13: El driver estaba en borrador al 20-ago. | N13: Ejercicio iniciado el 21-ago de 1:30 p.m. a 5:00 p.m. | O13: Por confirmar talla
A14: REQ-178 | B14: Transversal / Principios generales | C14: Plataforma | D14: Sprint 0 | E14: Definición del umbral de asertividad y de las métricas de calidad de los agentes que se aplicarán desde el Release 1. | G14: Debe tener | H14: M | I14: 5 | J14: Sprint 0 | K14: 46280 | L14: 46286 | M14: Valor exacto del umbral por definir. | N14: — | O14: Por confirmar talla
A15: REQ-180 | B15: Transversal / Principios generales | C15: Plataforma | D15: Sprint 0 | E15: Validación con el equipo técnico de los tallajes y estimaciones preliminares, y ajuste del backlog del Release 1 antes de iniciar la implementación. | G15: Debe tener | H15: M | I15: 5 | J15: Sprint 0 | K15: 46287 | L15: 46293 | M15: — | N15: — | O15: Por confirmar talla
A16: REQ-177 | B16: Gestor de Solicitud | C16: Solicitud | D16: Sprint 0 | E16: Decisión técnica del lector de IA a reutilizar (ADR vs. desarrollo de TT) y prueba de concepto de la extracción documental sobre documentos reales. | G16: Debe tener | H16: L | I16: 10 | J16: Sprint 0 | K16: 46266 | L16: 46279 | M16: Impactada por el recorte de presupuesto del equipo de salud modular. | N16: — | O16: Por confirmar talla
A17: REQ-076 | B17: Transversal / Principios generales | C17: Plataforma | D17: Release 1 | E17: Arquitectura de microservicios, agéntica, dirigida por eventos (EDA), moderna y desacoplada — se acopla a los cores existentes, no los reemplaza. | F17: Arquitectura | G17: Debe tener | H17: XL | I17: 20 | J17: S1–S2 | K17: 46296 | L17: 46324 | M17: — | N17: — | O17: Talla confirmada
A18: REQ-079 | B18: Transversal / Principios generales | C18: Plataforma | D18: Release 1 | E18: Demanda cruzada Cores para emisión de Eventos (Sura His, Siniestro Integral) | F18: Desarrollo de implementaciones en Cores de cara a los eventos | G18: Debe tener | H18: L | I18: 10 | J18: S1 | K18: 46303 | L18: 46310 | M18: Equipos Core para las demandas cruzadas | N18: — | O18: Talla confirmada
A19: REQ-082 | B19: Transversal / Principios generales | C19: Plataforma | D19: Release 1 | E19: Ajustes Siniestro Integral para que sea el canal unificado de Registro y seguimiento de solicitudes | F19: Desarrollo de implementación en siniestro integral | G19: Debe tener | H19: L | I19: 10 | J19: S2–S3 | K19: 46325 | L19: 46332 | M19: — | N19: — | O19: Talla confirmada
A20: REQ-009 | B20: Siniestro Integral | C20: Solicitud | D20: Release 1 | E20: Modelo de datos "padre-hijo": la solicitud es el padre; cada autorización por servicio/CUPS es un hijo con estado propio. | G20: Debe tener | H20: M | I20: 5 | J20: S1 | K20: 46296 | L20: 46302 | M20: — | N20: — | O20: Talla confirmada
A21: REQ-010 | B21: Gestor de Solicitud | C21: Solicitud | D21: Release 1 | E21: Recoger definiciones, lineamientos que tengamos en compañía y habilitadores que podamos reutilizar en la arquitectura. | F21: Lineamientos y habilitadores para la construcción del Gestor | G21: Debe tener | H21: L | I21: 10 | J21: S1 | K21: 46296 | L21: 46310 | M21: — | N21: — | O21: Talla confirmada
A22: REQ-011 | B22: Siniestro Integral | C22: Solicitud | D22: Release 1 | E22: Genera un ID temporal como número radicador (correlation ID), y almacena la información de forma temporal. | G22: Debe tener | H22: S | I22: 3 | J22: S1 | K22: 46296 | L22: 46300 | M22: — | N22: — | O22: Talla confirmada
A23: REQ-012 | B23: Siniestro Integral | C23: Solicitud | D23: Release 1 | E23: Lleva los documentos a P8. | G23: Debe tener | H23: XS | I23: 1 | J23: S1 | K23: 46296 | L23: 46296 | M23: — | N23: — | O23: Talla confirmada
A24: REQ-013 | B24: Siniestro Integral | C24: Solicitud | D24: Release 1 | E24: Publica el evento que activa al core de salud (SuraHis) para la generación de la solicitud; ese mismo evento alimenta el flujo de solicitud/autorización para la Torre de Control. | G24: Debe tener | H24: M | I24: 5 | J24: S1 | K24: 46297 | L24: 46303 | M24: — | N24: — | O24: Talla confirmada
A25: REQ-017 | B25: Gestor de Solicitud | C25: Solicitud | D25: Release 1 | E25: Habilitar plataforma necesaria por el Gestor solicitud | F25: Habilitar Tenant/Dominio capacidades para los agentes del Gestor de Solicitud(Plataforma agéntica) | G25: Debe tener | H25: XL | I25: 20 | J25: S1–S3 | K25: 46301 | L25: 46345 | M25: — | N25: — | O25: Talla confirmada
A26: REQ-065 | B26: Gestor de Solicitud | C26: Solicitud | D26: Release 1 | E26: Implementar el Gestor Solicitud (Agentes y herramientas) | F26: Agente implementado en el Gestor de Solicitud | G26: Debe tener | H26: L | I26: 10 | J26: S1–S2 | K26: 46303 | L26: 46317 | O26: Talla confirmada
A27: REQ-084 | B27: Gestor de Solicitud | C27: Solicitud | D27: Release 1 | E27: Despliegue del Agente en los diferentes ambientes | F27: Agente desplegado en el Gestor de Solicitud | G27: Debe tener | H27: M | I27: 5 | J27: S1 | K27: 46303 | L27: 46310 | M27: — | N27: — | O27: Talla confirmada
A28: REQ-086 | B28: Gestor de Solicitud | C28: Solicitud | D28: Release 1 | E28: Liberación agente | F28: Gestor productivo para el canal, operación y rol definidos | G28: Debe tener | H28: M | I28: 5 | J28: S1 | K28: 46304 | L28: 46311 | M28: — | N28: — | O28: Talla confirmada
A29: REQ-087 | B29: Gestor de Solicitud | C29: Solicitud | D29: Release 1 | E29: Entendimiento del proceso de Evaluación y sus requerimientos | F29: Información fundamental para la evaluación (Mínimos requeridos) | G29: Debe tener | H29: L | I29: 10 | J29: S1–S2 | K29: 46311 | L29: 46324 | M29: — | N29: — | O29: Talla confirmada
A30: REQ-001 | B30: Canales / Front Externos | C30: Canales | D30: Release 2 | E30: Comprobación de derechos (vigencia de póliza, mora) obligatoria al inicio del flujo, antes de pedir cualquier otro dato (se hace directamente desde el front). | G30: Debe tener | H30: M | I30: 5 | J30: S7 | K30: 46399 | L30: 46405 | M30: — | N30: — | O30: Por confirmar talla
A31: REQ-002 | B31: Canales / Front Externos | C31: Canales | D31: Release 2 | E31: Documentos aparentemente inválidos no permiten continuar con la creación de la solicitud (agente IA light). | G31: Debe tener | H31: L | I31: 10 | J31: S7 | K31: 46399 | L31: 46412 | M31: — | N31: — | O31: Por confirmar talla
A32: REQ-003 | B32: Canales / Front Externos | C32: Canales | D32: Release 2 | E32: Omnicanalidad real: el historial de solicitudes/autorizaciones debe verse igual sin importar el canal de origen. | G32: Debe tener | H32: S | I32: 3 | J32: S7 | K32: 46399 | L32: 46401 | M32: — | N32: — | O32: Por confirmar talla
A33: REQ-004 | B33: Canales / Front Externos | C33: Canales | D33: Release 2 | E33: No requiere segundo factor de autenticación en el flujo de solicitud desde la app (sí se evaluará para reembolsos, por implicar pago directo). | G33: Debe tener | H33: M | I33: 5 | J33: S7 | K33: 46402 | L33: 46408 | M33: — | N33: — | O33: Por confirmar talla
A34: REQ-005 | B34: Canales / Front Externos | C34: Canales | D34: Release 2 | E34: Front con/sin documentos dependiendo del tipo de servicio de cara al prestador; front con documentos de cara al asesor y al cliente. | G34: Debe tener | H34: M | I34: 5 | J34: S7 | K34: 46406 | L34: 46412 | M34: — | N34: — | O34: Por confirmar talla
A35: REQ-066 | B35: Gestor de Solicitud (Canales) | C35: Canales | D35: Release 2 | E35: Selección de prestador: el campo queda como opcional y se traslada a un paso posterior del flujo (después del OCR de los documentos adjuntos), donde ya se puede sugerir un prestador con datos precargados. | G35: Debe tener | H35: S | I35: 3 | J35: S7 | K35: 46409 | L35: 46413 | M35: — | N35: Acordado con equipo de Canales/UX (James, Andrea, Carlos) | O35: Por confirmar talla
A36: REQ-067 | B36: Gestor de Solicitud (Canales) | C36: Canales | D36: Release 2 | E36: Reestudio: aplica solo cuando la autorización fue negada y el asegurado no está de acuerdo; el sistema explica el motivo, el usuario adjunta nuevos documentos con motivo en texto libre, y la reevaluación la hace el mismo evaluador que negó el caso. Se diferencia de 'documentos pendientes', que ocurre durante la evaluación por falta de soportes. | G36: Debe tener | H36: M | I36: 5 | J36: S7–S8 | K36: 46413 | L36: 46419 | M36: — | N36: — | O36: Por confirmar talla
A37: REQ-068 | B37: Gestor de Solicitud (Canales) | C37: Canales | D37: Release 2 | E37: Notificación y visibilidad cruzada cliente-prestador: se notifica al cliente cuando un prestador radica una solicitud a su nombre; el cliente debe poder ver todo lo relacionado con su caso sin importar el canal de radicación, para evitar solicitudes duplicadas. | G37: Debe tener | H37: M | I37: 5 | J37: S7–S8 | K37: 46413 | L37: 46419 | M37: — | N37: — | O37: Por confirmar talla
A38: REQ-069 | B38: Gestor de Solicitud (Canales) | C38: Canales | D38: Release 2 | E38: Anulación de solicitudes: solo la puede hacer el prestador, y solo si el estado es 'en proceso'. El estado 'anulada' y su motivo deben ser visibles para el asegurado en lenguaje claro, incluyendo el caso de una autorización ya aprobada que se anula después. | G38: Debe tener | H38: S | I38: 3 | J38: S8 | K38: 46414 | L38: 46416 | M38: — | N38: — | O38: Por confirmar talla
A39: REQ-070 | B39: Gestor de Solicitud (Canales) | C39: Canales | D39: Release 2 | E39: Solicitud en el exterior: flujo distinto al general — no genera una autorización tradicional; llega a una bandeja de gestión que tramita con un proveedor externo y responde al asegurado por correo. | G39: Debe tener | H39: XL | I39: 20 | J39: S8–S10 | K39: 46419 | L39: 46444 | M39: Validar con el equipo de exterior si los campos/documentos pueden reutilizar el flujo general. | N39: Pendiente con Tania Saldarriaga (Negocio) | O39: Por confirmar talla
A40: REQ-071 | B40: Gestor de Solicitud (Canales) | C40: Canales | D40: Release 2 | E40: Caso especial de inclusión de recién nacido para atención urgente: flujo corto e independiente, fuera del flujo general de autorizaciones (se remite al equipo de Expedición). | G40: Debe tener | H40: M | I40: 5 | J40: S8 | K40: 46420 | L40: 46426 | M40: — | N40: — | O40: Por confirmar talla
A41: REQ-072 | B41: Gestor de Solicitud (Canales) | C41: Canales | D41: Release 2 | E41: 'Solicitar estado de cuenta' se renombra de cara al usuario (los asegurados lo conocen como 'certificado de antigüedad') y vive dentro del módulo transversal de certificados de activos digitales, sin duplicar arquitectura. | G41: Debe tener | H41: L | I41: 10 | J41: S8–S9 | K41: 46420 | L41: 46433 | M41: Nombre definitivo aún por decidir. | N41: — | O41: Por confirmar talla
... A178: REQ-117 | B178: Gestor de Prestación | C178: Prestación | D178: Fase posterior | E178: Integración con la cola de eventos de interoperabilidad de historia clínica (arquitectura 2.0) para conocer si el servicio autorizado fue efectivamente atendido, sin construir un componente tecnológico nuevo en Gestores. | G178: No debería | H178: XXL | I178: 30 | J178: S26–S28 | K178: 46710 | L178: 46752 | M178: — | N178: — | O178: Por confirmar talla
B180: Resumen
B181: Total requisitos | C181: =COUNTA(A6:A243) -> 173
B182: XS | C182: =COUNTIF(H6:H243,"XS") -> 5
B183: S | C183: =COUNTIF(H6:H243,"S") -> 34
B184: M | C184: =COUNTIF(H6:H243,"M") -> 65
B185: L | C185: =COUNTIF(H6:H243,"L") -> 43
B186: XL | C186: =COUNTIF(H6:H243,"XL") -> 20
B187: XXL | C187: =COUNTIF(H6:H243,"XXL") -> 6
B188: Total días hábiles | C188: =SUM(I6:I243) -> 1442
B189: Sprint 0 | C189: =COUNTIF(D6:D243,"Sprint 0") -> 11
B190: Release 1 | C190: =COUNTIF(D6:D243,"Release 1") -> 13
B191: Release 2 | C191: =COUNTIF(D6:D243,"Release 2") -> 78
B192: Release 3 | C192: =COUNTIF(D6:D243,"Release 3") -> 52
B193: Fase posterior | C193: =COUNTIF(D6:D243,"Fase posterior") -> 19
B194: Debe tener | C194: =COUNTIF(G6:G243,"Debe tener") -> 111

Sheet Equipos y Paralelización
A1: DISTRIBUCIÓN DE EQUIPOS Y ANÁLISIS DE PARALELIZACIÓN
A2: El número de requisitos, los días hábiles y la ventana real se calculan directamente desde 'Backlog-Estimación'. Cada squad aparece en una fila por release porque sus ventanas están separadas en el tiempo, pero es el mismo equipo. En el Release 1 se refuerzan los carriles (Solicitud 5, Plataforma 3) para sostener la ventana de dos meses. Propuesta de trabajo para la estimación de capacidad y costo — no refleja asignaciones acordadas.
A4: Squad | B4: Gestores que atiende | C4: Composición sugerida | D4: Carriles (paralelo) | E4: FTE aprox. | F4: N.° requisitos | G4: Días hábiles acumulados | H4: Sprint inicio | I4: Ventana real (calculada) | J4: ¿Paralelizable? | K4: Dependencia bloqueante
A5: Plataforma (Sprint 0) | B5: Transversal / Principios generales (EDA, APIs, MCP, contingencia) | C5: 1 arquitecto de solución · 1 arquitecto de datos · 2 ingenieros de plataforma | D5: 2 | E5: 3.5 | F5: 9 | G5: 65 | H5: S0 | I5: 01-Sep-26 a 28-Sep-26 | J5: Sí, con Solicitud desde S1 | K5: Sprint 0 debe haber dejado el catálogo de eventos y los contratos de API en borrador
A6: Plataforma (Release 1) | B6: Transversal / Principios generales (EDA, APIs, MCP, contingencia) | C6: 1 arquitecto de solución · 1 arquitecto de datos · 2 ingenieros de plataforma | D6: 3 | E6: 4.5 | F6: 8 | G6: 100 | H6: S1 | I6: 01-Oct-26 a 30-Nov-26 | J6: Sí, con Solicitud desde S1 | K6: Sprint 0 debe haber dejado el catálogo de eventos y los contratos de API en borrador
A7: Plataforma (Release 2) | B7: Transversal / Principios generales (EDA, APIs, MCP, contingencia) | C7: 1 arquitecto de solución · 1 arquitecto de datos · 2 ingenieros de plataforma | D7: 2 | E7: 3.5 | F7: 10 | G7: 108 | H7: S7 | I7: 12-Jan-27 a 01-Apr-27 | J7: Sí, con Solicitud desde S1 | K7: Sprint 0 debe haber dejado el catálogo de eventos y los contratos de API en borrador
A8: Solicitud (Sprint 0) | B8: Gestor de Solicitud · Siniestro Integral | C8: 1 tech lead · 3 desarrolladores backend · 1 desarrollador Flutter | D8: 4 | E8: 6 | F8: 1 | G8: 10 | H8: S0 | I8: 01-Sep-26 a 14-Sep-26 | J8: Sí, con Plataforma desde S1 | K8: Requiere ambientes, equipo capacitado y lector de IA seleccionado en Sprint 0
A9: Solicitud (Release 1) | B9: Gestor de Solicitud · Siniestro Integral | C9: 1 tech lead · 3 desarrolladores backend · 1 desarrollador Flutter | D9: 5 | E9: 7 | F9: 12 | G9: 109 | H9: S1 | I9: 01-Oct-26 a 19-Nov-26 | J9: Sí, con Plataforma desde S1 | K9: Requiere ambientes, equipo capacitado y lector de IA seleccionado en Sprint 0
A10: Solicitud (Release 2) | B10: Gestor de Solicitud · Siniestro Integral | C10: 1 tech lead · 3 desarrolladores backend · 1 desarrollador Flutter | D10: 4 | E10: 6 | F10: 29 | G10: 227 | H10: S7 | I10: 12-Jan-27 a 09-Apr-27 | J10: Sí, con Plataforma desde S1 | K10: Requiere ambientes, equipo capacitado y lector de IA seleccionado en Sprint 0
A11: Canales (Sprint 0) | B11: Canales / Front Externos · Gestor de Solicitud (Canales) | C11: 1 UX/UI · 3 desarrolladores front (Flutter/web) | D11: 3 | E11: 5 | F11: 1 | G11: 5 | H11: S0 | I11: 01-Sep-26 a 07-Sep-26 | J11: Sí, desde el Release 2 | K11: En Release 1 se reutilizan los canales existentes; depende de la estimación de esfuerzo de James
A12: Canales (Release 2) | B12: Canales / Front Externos · Gestor de Solicitud (Canales) | C12: 1 UX/UI · 3 desarrolladores front (Flutter/web) | D12: 3 | E12: 5 | F12: 13 | G12: 84 | H12: S7 | I12: 12-Jan-27 a 26-Feb-27 | J12: Sí, desde el Release 2 | K12: En Release 1 se reutilizan los canales existentes; depende de la estimación de esfuerzo de James
A13: Evaluación | B13: Gestor de Evaluación | C13: 1 tech lead · 2 desarrolladores backend · 1 ingeniero de IA | D13: 3 | E13: 4.5 | F13: 26 | G13: 283 | H13: S7 | I13: 12-Jan-27 a 08-Jun-27 | J13: Sí, en paralelo con Canales en Release 2 | K13: Su mínimo viable se estimó en ~4 meses; requiere el modelo de datos y eventos del Release 1 estables
A14: Coordinación | B14: Gestor de Coordinación · Gestor de Asignación (interno) | C14: 1 tech lead · 2 desarrolladores backend | D14: 2 | E14: 3.5 | F14: 22 | G14: 160 | H14: S15 | I14: 20-May-27 a 16-Sep-27 | J14: Sí, con Torre de Control en Release 3 | K14: Consume la salida de la decisión de autorización de Evaluación
A15: Torre de Control | B15: Gestor de Monitoreo (Torre de Control) · Datalake (Transversal) | C15: 1 tech lead · 2 desarrolladores backend · 1 ingeniero de datos | D15: 3 | E15: 4.5 | F15: 30 | G15: 188 | H15: S17 | I15: 23-Jun-27 a 24-Sep-27 | J15: Parcial: la capa de consolidación puede adelantarse | K15: Necesita que todos los gestores publiquen eventos con contrato estable
A16: Prestación | B16: Gestor de Prestación | C16: 1 tech lead · 1 desarrollador backend | D16: 2 | E16: 2.5 | F16: 9 | G16: 131 | H16: S22 | I16: 13-Sep-27 a 31-Dec-27 | J16: No es prioridad del alcance actual | K16: Fuera del alcance del caso de negocio vigente
A17: Finalización | B17: Gestor de Finalización | C17: 1 tech lead · 1 desarrollador backend | D17: 2 | E17: 2.5 | F17: 10 | G17: 67 | H17: S22 | I17: 13-Sep-27 a 29-Oct-27 | J17: No se implementa en el primer alcance de salud | K17: Representado con líneas punteadas; lo dispara el primer negocio que lo requiera
C18: TOTAL FTE (por squad único, sin doble conteo de Canales) | E18: 34 | F18: =SUM(F5:F17) -> 180
C20: Nota | D20: Canales aparece en dos filas (Release 1 y Release 2) porque trabaja en dos olas separadas en el tiempo, pero es el mismo equipo: su FTE se cuenta una sola vez en el total. El FTE total tampoco es la capacidad simultánea: los squads de Release 2 y 3 pueden conformarse reasignando personas de los squads de Release 1 ya liberados.
A23: LÍNEA DE TIEMPO POR SQUAD
L24: Squad | M24: S1 | N24: S2 | O24: S3 | P24: S4 | Q24: S5 | R24: S6 | S24: S7 | T24: S8 | U24: S9 | V24: S10 | W24: S11 | X24: S12 | Y24: S13 | Z24: S14 | AA24: S15 | AB24: S16 | AC24: S17 | AD24: S18 | AE24: S19 | AF24: S20 | AG24: S21 | AH24: S22 | AI24: S23 | AJ24: S24
L25: Plataforma (Sprint 0)
L26: Plataforma (Release 1)
L27: Plataforma (Release 2)
L28: Solicitud (Sprint 0)
L29: Solicitud (Release 1)
L30: Solicitud (Release 2)
L31: Canales (Sprint 0)
L32: Canales (Release 2)
L33: Evaluación
L34: Coordinación
L35: Torre de Control
L36: Prestación
... L49: 9. SuraHis atraviesa todos los releases como dependencia externa. El acuerdo formal de capacidad es una actividad explícita del Sprint 0 porque sin él ninguna de estas fechas se sostiene.

Sheet Requisitos Funcionales
A1: REQUISITOS FUNCIONALES POR GESTOR
A2: Requisitos del archivo v2 (12-ago) más las definiciones funcionales nuevas de las sesiones del 18 al 20 de agosto, agregadas al final en el bloque azul.
A4: Gestor / Frente | B4: Requisito funcional (regla de negocio) | C4: Duda / nota abierta en el PPT | D4: Estado | E4: Decisión / Seguimiento
A5: Canales / Front Externos | B5: Comprobación de derechos (vigencia de póliza, mora) obligatoria al inicio del flujo, antes de pedir cualquier otro dato (se hace directamente desde el front). | D5: Definido
A6: Canales / Front Externos | B6: Documentos aparentemente inválidos no permiten continuar con la creación de la solicitud (agente IA light). | D6: Definido
A7: Canales / Front Externos | B7: Omnicanalidad real: el historial de solicitudes/autorizaciones debe verse igual sin importar el canal de origen. | D7: Definido
A8: Canales / Front Externos | B8: No requiere segundo factor de autenticación en el flujo de solicitud desde la app (sí se evaluará para reembolsos, por implicar pago directo). | D8: Definido
A9: Canales / Front Externos | B9: Front con/sin documentos dependiendo del tipo de servicio de cara al prestador; front con documentos de cara al asesor y al cliente. | D9: Definido
A10: Gestor de Solicitud | B10: Recibe solicitudes de 3 públicos: prestador (70-80% del volumen, foco prioritario), cliente/asegurado (~15%) y asesor (~5%, tendencia a minimizarse). | D10: Definido
A11: Gestor de Solicitud | B11: Meta: pedir solo identificación (aplica solo para prestador y asesor) + 2 documentos (historia clínica y orden médica); el cliente nunca digita datos, solo adjunta. | D11: Definido
A12: Gestor de Solicitud | B12: Documento no legible nunca bloquea al usuario: siempre pasa a bandeja de revisión manual. | D12: Definido
A13: Siniestro Integral | B13: Modelo de datos "padre-hijo": la solicitud es el padre; cada autorización por servicio/CUPS es un hijo con estado propio. | D13: Definido
A14: Gestor de Solicitud | B14: Extrae mediante agente IA la información de los documentos adjuntos (orden médica + historia clínica). | D14: Definido
A15: Siniestro Integral | B15: Genera un ID temporal como número radicador (correlation ID), y almacena la información de forma temporal. | D15: Definido
A16: Siniestro Integral | B16: Lleva los documentos a P8. | D16: Definido
A17: Siniestro Integral | B17: Publica el evento que activa al core de salud (SuraHis) para la generación de la solicitud; ese mismo evento alimenta el flujo de solicitud/autorización para la Torre de Control. | D17: Definido
A18: Siniestro Integral | B18: Autorización automática (algunas no requieren soportes) en servicios clasificados como "nivel 1"; para los niveles 3 y 4 (alto costo/riesgo) siempre van a evaluación manual. | D18: Definido | E18: Sin cambios esta semana — se mantiene 'por validar' con Negocio.
A19: Siniestro Integral | B19: Integralidad automática con EPS Sura cuando la póliza voluntaria no cubre el servicio y se genera la negación de una solicitud (régimen contributivo activo). | C19: Validar con Negocio, dado que se trabaja desde SuraHis. | D19: Por validar
A20: Gestor de Solicitud | B20: Nueva funcionalidad "Reestudio": permite pedir reevaluación de una solicitud negada adjuntando nueva evidencia u observaciones. | C20: Revisemos con Negocio. | D20: Por validar
A21: Gestor de Solicitud | B21: Si la IA no identifica el documento con certeza, el caso va a bandeja manual sin notificar al asegurado que el documento es inválido (evita falsos negativos); solo se notifica si hay certeza de que el documento no corresponde. | D21: Definido en sesión 10-ago
A22: Gestor de Solicitud | B22: Se incorpora como requisito funcional el "rescate de la solicitud" cuando la radicación no se concluye, sin importar en qué paso quede (antes no estaba documentado). | D22: Definido en sesión 10-ago
A23: Gestor de Evaluación | B23: Consulta al Core (SuraHis) coberturas, vigencias, convenios y exclusiones para los controles de evaluación. | D23: Definido
A24: Gestor de Evaluación | B24: Valida la pertinencia médica; decide autorizar, negar o escalar a evaluación manual (coherencia orden médica/historia clínica, CIE-10/CUPS, score de complejidad). | D24: Definido
A25: Gestor de Evaluación | B25: Regla crítica: la negación nunca se hace 100% automática — toda negación exige intervención de un evaluador humano (administrativa vs. por pertinencia médica). | D25: Definido
A26: Gestor de Evaluación | B26: Revisar la integración para consultar mora (ir directamente al core de PDN o pasar por SuraHis). | D26: Por validar
A27: Gestor de Evaluación | B27: Niveles de escalamiento: Nivel 1 automático · Nivel 2 administrativo · Niveles 3 (enfermeras/instrumentadoras) y 4 (médicos/especialistas). | C27: ¿Está incluido dentro del alcance de Gestores o de SuraHis? | D27: Por validar | E27: Definido parcialmente (12-ago): para Release 1 el nivel 2/3/4 se resuelve como función de SuraHis; el gestor consume vía API. Falta validar con negocio.
A28: Gestor de Evaluación | B28: El agente entrega un "concepto"/resumen de su análisis al escalar a la bandeja manual, para acelerar la revisión humana. | D28: Definido
A29: Gestor de Evaluación | B29: No genera el número de solicitud de autorización/negación: deja el caso listo vía evento — el consecutivo lo genera SuraHis. | D29: Definido
A30: Gestor de Evaluación | B30: Reutiliza el homologador de CUPS y el motor ya productivo del proyecto de autorizaciones EPS, en vez de partir de cero. | D30: Definido
A31: Gestor de Evaluación | B31: Valida duplicidad (mismo prestador/documentos o mismo tipo de servicio) consultando histórico en SuraHis; casos sospechosos van a bandeja manual con nivel + prioridad + explicación, sin negación automática. | C31: Falta definir con negocio/equipo médico la ventana de tiempo y el criterio exacto por tipo de servicio. | D31: Definido en sesión 10-ago
A32: Gestor de Asignación (diapositiva oculta en el PPT original) | B32: La asignación al equipo se distribuye según reglas de criticidad (marcas en salud, PEP, edad del asegurado, urgencia, quejas/tutelas, diagnósticos de riesgo) entre evaluadores disponibles por nivel. | C32: Se declara en el PPT original que esta función "va en SuraHis". | D32: Por validar / posible duplicado con SuraHis
A33: Gestor de Asignación (diapositiva oculta en el PPT original) | B33: Para solicitudes pendientes por gestión se habilita la reasignación entre niveles. | D33: Por validar / posible duplicado con SuraHis
A34: Gestor de Asignación (diapositiva oculta en el PPT original) | B34: Cada solicitud debe tener un tiempo de respuesta asignado (100% de las solicitudes en menos de 24 horas). | D34: Por validar / posible duplicado con SuraHis
A35: Gestor de Asignación (diapositiva oculta en el PPT original) | B35: Se debe habilitar la opción de solicitud de requisitos (notificar al cliente); al adjuntar el soporte, se encola de nuevo con prioridad alta. | D35: Por validar / posible duplicado con SuraHis
A36: Gestor de Asignación (diapositiva oculta en el PPT original) | B36: Con la negación de un servicio se debe activar la radicación automática de la solicitud de integralidad a EPS Sura. | D36: Por validar / posible duplicado con SuraHis
A37: Gestor de Asignación (diapositiva oculta en el PPT original) | B37: Se debe habilitar la opción de resignación manual de solicitudes a otro evaluador (novedades con el evaluador asignado inicialmente). | D37: Por validar / posible duplicado con SuraHis
A38: Gestor de Asignación (diapositiva oculta en el PPT original) | B38: La notificación al cliente por incumplimiento de SLA se dispara vía evento publicado por la Torre de Control; el canal (WhatsApp/app) entrega el mensaje, no el gestor. | C38: Pendiente validar arquitectura de eventos con Víctor. | D38: Definido en sesión 10-ago
A39: Gestor de Coordinación | B39: Direcciona el servicio ya autorizado al prestador adecuado: simple (un solo prestador posible, sin IA) o múltiple (evalúa tarifa/cercanía/especialización, con IA). | D39: Definido
A40: Gestor de Coordinación | B40: 3 casos de negocio: producto modular (direccionamiento automático) · clásica/global (cliente elige, se valida convenio) · sin preferencia (se recomienda el mejor). | D40: Definido
A41: Gestor de Coordinación | B41: Criterios de priorización de prestadores: quejas (Medallia), satisfacción, disponibilidad de citas, "suficiencia de la red" y tarifa del prestador. | D41: Definido
A42: Gestor de Coordinación | B42: Si el prestador elegido no tiene convenio vigente, se asigna automáticamente el mejor rankeado y se notifica al cliente. | D42: Definido
A43: Gestor de Coordinación | B43: Si no hay red contratada en la ciudad, se recomienda la ciudad más cercana o se escala a Convenios (bandeja de convenios en SuraHis). | D43: Definido
A44: Gestor de Coordinación | B44: Notifica tanto al asegurado (prestador asignado) como al prestador (autorización pendiente de atender). | D44: Definido
A45: Gestor de Coordinación | B45: Objetivo estratégico: mapear automáticamente la autorización contra el convenio/tarifa para pagar más rápido y reducir glosas. | D45: Definido
A46: Gestor de Prestación | B46: Da seguimiento al "momento de verdad": si la cita fue programada, si el paciente asistió, novedades del servicio. | C46: Si esto se quiere, se debe mover a Torre de Control. | D46: Por validar
A47: Gestor de Prestación | B47: Mecanismo actual: confirmación por QR escaneado por el asegurado (piloto ya finalizado, solo consulta externa). | D47: Definido (piloto)
A48: Gestor de Prestación | B48: Se evalúa evolucionar a clave dinámica (doble factor, ya disponible en la app) como mecanismo de confirmación de atención. | D48: En evaluación
A49: Gestor de Prestación | B49: Visión ideal (aún no lograda ni por EPS): OTP de asistencia + interoperabilidad directa con el sistema propio del prestador. | D49: Aspiracional / no logrado
A50: Gestor de Prestación | B50: Mecanismo de registro de asistencia en SuraHis. | C50: Completar con las conclusiones del 05 de agosto (nota ya marcada en el PPT original). | D50: Pendiente completar
A51: Gestor de Monitoreo (Torre de Control) | B51: Renombrado de "Monitoreo" a "Torre de Control" por ampliación de alcance durante las sesiones. | D51: Sin iniciar (a la fecha del PPT)
A52: Gestor de Monitoreo (Torre de Control) | B52: Monitorea el ciclo de vida completo de la autorización: cumplimiento de SLA/ANS, carga de trabajo y trazabilidad. | D52: Sin iniciar (a la fecha del PPT)
A53: Gestor de Monitoreo (Torre de Control) | B53: Regla explícita: no se monitorea todo lo que llega, solo lo que "se sale de lo esperado" — la criticidad varía por tipo de caso. | D53: Sin iniciar (a la fecha del PPT)
A54: Gestor de Monitoreo (Torre de Control) | B54: Visión ampliada: capacidades proactivas (contactar directamente al cliente/prestador) y potestad de intervenir otros gestores. | D54: Sin iniciar (a la fecha del PPT)
A55: Gestor de Monitoreo (Torre de Control) | B55: Responsable de detectar comportamiento anómalo de los agentes (ej. ratio de rechazos fuera de lo normal) y activar mejora continua. | D55: Sin iniciar (a la fecha del PPT)
A56: Gestor de Monitoreo (Torre de Control) | B56: Expone información distinta según el actor consultante (prestador, cliente, asesor), enmascarando datos sensibles. | D56: Sin iniciar (a la fecha del PPT)
A57: Gestor de Monitoreo (Torre de Control) | B57: Rescate digital automático: si falla el canal al radicar, contacta por WhatsApp/app para continuar el proceso, sin pasar por bandeja manual. | D57: Definido en sesión 10-ago
A58: Gestor de Monitoreo (Torre de Control) | B58: Detecta solicitudes repetidas (2 o más veces) con las mismas características y activa el mismo flujo de rescate con mensaje diferenciado. | D58: Definido en sesión 10-ago
A59: Gestor de Monitoreo (Torre de Control) | B59: Notificaciones basadas en eventos: el Core informa tiempos por etapa, la Torre de Control detecta incumplimiento de SLA y publica un evento (no notifica directo; lo hace el canal que lo consume). | C59: Pendiente validar formalmente con Víctor (arquitectura). | D59: Definido en sesión 10-ago / por validar arquitectura
A60: Gestor de Monitoreo (Torre de Control) | B60: Notifica al asegurado ante incumplimiento de SLA (mensaje de acompañamiento) y alerta internamente a evaluadores/líderes por casos por vencer o desborde de capacidad. | D60: Definido en sesión 10-ago
A61: Gestor de Monitoreo (Torre de Control) | B61: Requiere vista individual (línea de tiempo por solicitud) y vista grupal/masiva (operación agregada) para habilitar gestión proactiva. | D61: Definido en sesión 10-ago
A62: Gestor de Finalización | B62: Es el gestor menos desarrollado de los 6 — solo definición conceptual, sin sesión de estructuración dedicada en el período revisado. | D62: Sin iniciar
A63: Gestor de Finalización | B63: 3 pilares: satisfacción del cliente · conciliación y pago a proveedor (cuentas médicas) · pagos al cliente (reembolsos, fuera del MVP). | D63: Sin iniciar
A64: Gestor de Finalización | B64: Equivale, en autorizaciones, al pago de la cuenta médica: el prestador carga la factura con detalle de servicios y RIPS. | D64: Sin iniciar
A65: Gestor de Finalización | B65: Objetivo: que autorización y tarifa contratada queden tan conectadas que no haya que glosar ni devolver facturas. | D65: Sin iniciar
A66: Gestor de Finalización | B66: El fraude también puede materializarse aquí (sobrefacturación, sobretratamiento) — debe tratarse como transversal, no solo un punto. | D66: Sin iniciar
A67: Gestor de Finalización | B67: Se propone reutilizar el agente ya existente en EPS que lee/transcribe autorizaciones y valida contra CUPS. | D67: Sin iniciar
A68: Gestor de Solicitud | B68: Modelo de 'solicitud laxa': la solicitud se crea con campos comodín (valores 'desconocido') que se completan progresivamente a medida que el gestor o una persona los identifica; solo se materializa como solicitud formal en el core al alcanzar completitud. | D68: Nuevo — Definido en sesión técnica 12-ago | E68: Falta formalizar en documento de arquitectura y validar con negocio los campos considerados críticos
A69: Gestor de Solicitud | B69: La bandeja de solicitud incompleta tiene bloqueo por exclusión mutua (mutex) mientras un analista/agente la trabaja, y un tiempo de vida (TTL) tras el cual se libera y puede escalarse. | C69: Falta definir con negocio el valor exacto del TTL y el criterio de escalamiento por tipo de caso. | D69: Nuevo — Definido en sesión técnica 12-ago | E69: Por validar con negocio (ver hoja de Pendientes y Conversaciones)
A70: Gestor de Solicitud (Canales) | B70: Selección de prestador: el campo queda como opcional y se traslada a un paso posterior del flujo (después del OCR de los documentos adjuntos), donde ya se puede sugerir un prestador con datos precargados. | D70: Nuevo — Definido en sesión 11-ago | E70: Acordado con equipo de Canales/UX (James, Andrea, Carlos)
A71: Gestor de Solicitud (Canales) | B71: Reestudio: aplica solo cuando la autorización fue negada y el asegurado no está de acuerdo; el sistema explica el motivo, el usuario adjunta nuevos documentos con motivo en texto libre, y la reevaluación la hace el mismo evaluador que negó el caso. Se diferencia de 'documentos pendientes', que ocurre durante la evaluación por falta de soportes. | D71: Nuevo — Definido en sesión 11-ago
A72: Gestor de Solicitud (Canales) | B72: Notificación y visibilidad cruzada cliente-prestador: se notifica al cliente cuando un prestador radica una solicitud a su nombre; el cliente debe poder ver todo lo relacionado con su caso sin importar el canal de radicación, para evitar solicitudes duplicadas. | D72: Nuevo — Definido en sesión 11-ago
A73: Gestor de Solicitud (Canales) | B73: Anulación de solicitudes: solo la puede hacer el prestador, y solo si el estado es 'en proceso'. El estado 'anulada' y su motivo deben ser visibles para el asegurado en lenguaje claro, incluyendo el caso de una autorización ya aprobada que se anula después. | D73: Nuevo — Definido en sesión 11-ago
A74: Gestor de Solicitud (Canales) | B74: Solicitud en el exterior: flujo distinto al general — no genera una autorización tradicional; llega a una bandeja de gestión que tramita con un proveedor externo y responde al asegurado por correo. | C74: Validar con el equipo de exterior si los campos/documentos pueden reutilizar el flujo general. | D74: Nuevo — Definido en sesión 11-ago | E74: Pendiente con Tania Saldarriaga (Negocio)
A75: Gestor de Solicitud (Canales) | B75: Caso especial de inclusión de recién nacido para atención urgente: flujo corto e independiente, fuera del flujo general de autorizaciones (se remite al equipo de Expedición). | D75: Nuevo — Definido en sesión 11-ago
A76: Gestor de Solicitud (Canales) | B76: 'Solicitar estado de cuenta' se renombra de cara al usuario (los asegurados lo conocen como 'certificado de antigüedad') y vive dentro del módulo transversal de certificados de activos digitales, sin duplicar arquitectura. | C76: Nombre definitivo aún por decidir. | D76: Nuevo — Definido en sesión 11-ago
A77: Gestor de Coordinación / Asignación | B77: Para el Release 1, la asignación interna de casos a evaluadores/niveles la resuelve SuraHis; el gestor de Coordinación/Distribución consume esa asignación como herramienta vía API (sin duplicar la lógica). La evolución a otros cores/negocios queda prevista para fases futuras. | C77: Aclara si 'Asignación' (interno) y 'Coordinación' (externo) son la misma función. | D77: Nuevo — Definido en sesión técnica 12-ago | E77: Falta validación formal con negocio
A78: Gestor de Prestación | B78: El gestor de Prestación no se implementa como componente agéntico independiente para el alcance del MVP: la confirmación de atención se resuelve por integración directa Core-Core (SuraHis Prestación ↔ SuraHis Voluntarios) o por interoperabilidad de historia clínica (hoy solo consulta externa). | C78: Persiste incertidumbre de Daimer Munera sobre si a futuro debería tener capacidad agéntica propia. | D78: Nuevo — Definido en sesiones 11 y 12-ago | E78: Ver hoja de Pendientes y Conversaciones — tema no cerrado del todo
A79: Gestor de Monitoreo (Torre de Control) | B79: La Torre de Control no emite los eventos de cambio de estado (los emite el componente dueño de ese estado); se alimenta de ellos, toma decisiones, genera accionables/comandos/mensajes y construye vistas materializadas de trazabilidad y observabilidad. | D79: Nuevo — Definido (respuesta de arquitectura compartida 11-ago) | E79: Aplicar de forma consistente a todos los gestores
A80: NUEVOS — definiciones de las sesiones del 18 al 20 de agosto de 2026 (23 requisitos funcionales)
A81: Gestor de Solicitud | B81: Alcance acotado del primer entregable de diciembre: radicar una solicitud de autorización para un rol y un canal específicos, dejando modificaciones y otros trámites para un entregable posterior. | C81: ¿Se valida acotar el primer entregable al gestor de Solicitud, por un rol y un canal específicos? | D81: Nuevo — Propuesta en sesión 18-ago | E81: Refinar y validar internamente antes de someterla a negocio/TI (Tania, Sebastián, Vivi) · Diferido al Release 2 por capacidad del MVP de diciembre
A82: Gestor de Solicitud | B82: El agente receptor no asume que los archivos llegan bien identificados ni separados: debe detectar historia clínica y orden en un solo PDF, en desorden, comprimidos en ZIP o cifrados con contraseña (usualmente la cédula del paciente). | C82: Cómo manejar archivos cifrados cuando la contraseña no viene indicada en observaciones. | D82: Nuevo — Definido en sesión 19-ago | E82: Depende de que el agente infiera la contraseña vía razonamiento en lenguaje natural · Diferido al Release 2 por capacidad del MVP de diciembre
A83: Gestor de Solicitud | B83: Modelo asíncrono de bandeja de solicitudes (recibida / notificación cuando requiere atención) en lugar de un flujo sincrónico en línea, para no exponer al usuario a la latencia del procesamiento. | D83: Nuevo — Definido en sesión 19-ago | E83: Decisión de experiencia acordada en la sesión · Diferido al Release 2 por capacidad del MVP de diciembre
A84: Gestor de Solicitud | B84: Alertar al asegurado cuando el documento cargado no corresponde a lo esperado, sin afectar su experiencia ni bloquear la radicación. | D84: Nuevo — Definido en sesión 19-ago | E84: Diferido al Release 2 por capacidad del MVP de diciembre
A85: Gestor de Solicitud | B85: No hay rechazo automático: todo lo que el agente no puede resolver pasa a bandeja humana indicando por qué. Es el humano quien decide rechazar, rescatar información con el usuario o cancelar; la cancelación queda fuera del alcance del gestor. | D85: Nuevo — Definido en sesión 19-ago | E85: Diferido al Release 2 por capacidad del MVP de diciembre
A86: Gestor de Solicitud | B86: Capa de auditoría: analiza el histórico de solicitudes y reporta patrones a la Torre de Control (ej. porcentaje de casos en los que no se logró extraer el CUPS). Inicialmente es observabilidad pasiva, sin capacidad de decisión. | D86: Nuevo — Definido en sesión 19-ago | E86: Se descarta la auto-reparación activa en el alcance inicial · Diferido al Release 2 por capacidad del MVP de diciembre
A87: Gestor de Solicitud | B87: Umbral de asertividad: cada campo extraído viene con un porcentaje de confianza. Solo por encima del umbral definido (referencia discutida: 90%) el gestor actúa de forma autónoma; por debajo pasa a flujo humano, incluso si la tarea aparenta estar completa y el campo con baja confianza es crítico (ej. CUPS). | C87: Valor exacto del umbral por definir. | D87: Nuevo — Definido en sesión 19-ago | E87: Diferido al Release 2 por capacidad del MVP de diciembre
A88: Gestor de Solicitud | B88: Mecanismo de muestreo humano sobre los casos que el agente resuelve correctamente, no solo sobre los rechazos, para verificar que los aciertos realmente lo son. | C88: Hoy nadie revisa los casos resueltos bien, por lo que no hay certeza de su calidad. | D88: Nuevo — Definido en sesión 19-ago
A89: Gestor de Evaluación | B89: Capa de duplicados determinística, sin componente de IA: aplica reglas de negocio por especialidad y ventana de tiempo (ej. dos citas con el mismo especialista en un lapso corto cuentan como duplicado aunque sean solicitudes distintas). | D89: Nuevo — Definido en sesión 19-ago
A90: Gestor de Evaluación | B90: El gestor no rellena información faltante ni garantiza la completitud de la información: entra a operar cuando los atributos sobre la información ya están garantizados o descartados. | D90: Nuevo — Definido en sesión 19-ago
A91: Gestor de Evaluación | B91: Si durante la evaluación falta un dato que no era obligatorio en la solicitud pero sí es necesario para aplicar una regla de pertinencia (ej. peso o edad), no se devuelve la solicitud: se envía a bandeja humana indicando qué dato faltó y para qué regla. | C91: Sin ejemplo real validado con negocio. | D91: Nuevo — Definido en sesión 19-ago
A92: Gestor de Evaluación | B92: Evaluación estructurada en dos llamados al core en paralelo: reglas duras (producto, diagnóstico, CIE-10, cédula, vigencia de póliza, pagos — motor de reglas sin componente agéntico) y pertinencia médica (con componente agéntico: interpretación semántica de exclusiones, carencias y preexistencias descritas en texto libre). Solo si ambas se cumplen la solicitud pasa a la bandeja de autorizaciones. | D92: Nuevo — Definido en sesión 19-ago | E92: Si alguna falla, va a bandeja humana con la nota correspondiente
A93: Gestor de Evaluación | B93: La bandeja de 'listo para coordinación' tras una evaluación exitosa es la misma bandeja de 'pago automático'. | D93: Nuevo — Aclarado en sesión 20-ago
A94: Gestor de Evaluación | B94: Auditoría de decisiones automáticas: detectar desviaciones estadísticas y realizar revisión manual periódica por muestreo, especialmente en pertinencia médica, por riesgo de fraude sobre autorizaciones marcadas como automáticas que nunca se revisan. | D94: Nuevo — Definido en sesión 20-ago | E94: Aplica tanto a lo que el agente rechaza como a lo que acepta, y a todos los agentes que se monten
A95: Gestor de Monitoreo (Torre de Control) | B95: Controlar los niveles de autonomía de los gestores agénticos. | D95: Nuevo — Definido en sesión 19-ago
A96: Gestor de Monitoreo (Torre de Control) | B96: Entregar información a distintos canales en el lenguaje requerido por cada actor, registrando canal de destino, fecha de envío, tipo de mensaje y resultado de entrega (WhatsApp, correo, portal cliente, portal prestador y notificación interna al equipo). | D96: Nuevo — Definido en sesión 19-ago
A97: Gestor de Monitoreo (Torre de Control) | B97: Detección de anomalías y fraude como capacidad agéntica, aprovechando la vista panorámica que el core no tendría capacidad dedicada para generar. | C97: A qué nivel debe operar la detección (histórico vía Data Lake vs. inmediato desde otras fuentes). | D97: Nuevo — Definido en sesión 19-ago
A98: Gestor de Monitoreo (Torre de Control) | B98: Medir KPIs de eficiencia y productividad: tiempo de ciclo promedio, tiempo de espera, tiempo de atención y casos procesados, cerrados y abiertos por actor. | C98: Definición formal de los indicadores de la capa de correlación/insights aún pendiente. | D98: Nuevo — Propuesta en sesión 19-ago
A99: Gestor de Monitoreo (Torre de Control) | B99: Reportar a los líderes de operación cuando un equipo esté saturado o dejando de recibir autorizaciones. | C99: Dónde verán esos reportes: ¿visual aparte, dentro de SuraHis, o correo? | D99: Nuevo — Abierto (19-ago)
A100: Gestor de Monitoreo (Torre de Control) | B100: Detectar cuentas por pagar próximas a vencer y generar alertas, evitando llamadas de prestadores preguntando por pagos demorados. | D100: Nuevo — Definido en sesión 20-ago | E100: Ejemplo de valor de negocio planteado por Johny Zuleta
A101: Gestor de Evaluación | B101: La solicitud de autorización se desglosa en autorizaciones asociadas a un solo servicio, no a nivel de ítem o insumo individual (salvo la excepción de EPS, que desglosa a mayor detalle por temas legales). | C101: Cómo entregará el nuevo core las autorizaciones al gestor: una por una por procedimiento o agrupadas por paquete. | D101: Nuevo — Definido en sesión 20-ago
...

Sheet Requisitos No Funcionales
A1: REQUISITOS NO FUNCIONALES Y DE ARQUITECTURA
A2: Requisitos técnicos del archivo v2 (12-ago) más las definiciones de arquitectura nuevas de las sesiones del 18 al 20 de agosto, incluidas las actividades del Sprint 0.
A4: Gestor / Frente | B4: Requisito técnico / arquitectura | C4: Nota / pregunta abierta | D4: Estado | E4: Decisión / Seguimiento
A5: Transversal / Principios generales | B5: Arquitectura de microservicios, agéntica, dirigida por eventos (EDA), moderna y desacoplada — se acopla a los cores existentes, no los reemplaza. | D5: Definido
A6: Transversal / Principios generales | B6: Principio "coreless": la lógica de negocio (reglas, políticas, convenios) se desacopla de los cores legados hacia dominios agénticos. | D6: Definido
A7: Transversal / Principios generales | B7: El core (SuraHis) debe ser la fuente de la verdad transaccional, no el motor de reglas — principio validado repetidamente por arquitectura. | D7: Definido
A8: Transversal / Principios generales | B8: Riesgo/premisa explícita: el proyecto solo tiene sentido si los cores implementan la capacidad de exponer información vía API a tiempo. | D8: Premisa crítica / riesgo
A9: Transversal / Principios generales | B9: Cada gestor tendría base de datos propia, independiente y desacoplada. | C9: El patrón de acceso entre gestores aún no está cerrado. | D9: Por cerrar
A10: Transversal / Principios generales | B10: Se reutiliza la arquitectura de "Siniestro Integral" (Front + Back, API Gateway, orquestador, storage, colas) como base común de varios gestores. | D10: Definido
A11: Transversal / Principios generales | B11: Se privilegia un front único reutilizable por canal/actor, en lugar de un front independiente por cada gestor. | D11: Definido
A12: Transversal / Principios generales | B12: Diferenciación explícita comando (síncrono, se consume y desaparece) vs. evento (inmutable, usado para trazabilidad). | D12: Definido
A13: Gestor de Solicitud | B13: Front nuevo (Flutter), embebido en Sucursal Virtual Personas, AVA y Portal de Prestadores; reutiliza el back/orquestador de Siniestro Integral. | D13: Definido
A14: Gestor de Solicitud | B14: Flujo: Front → Storage temporal de documentos → integración asíncrona con P8; PoC en curso con Oracle 23/26 AI (IA embebida) como alternativa. | D14: En PoC
A15: Gestor de Solicitud | B15: Comprobación de derechos vía API de SuraHis (no Global Web) — mayor resiliencia y flexibilidad ante cambios futuros de core. | D15: Definido
A16: Gestor de Solicitud | B16: OCR/IA: LLM multimodal interpreta documentos directamente (15-40 seg); reutiliza el agente de pre-radicación de EPS (~93% de precisión). | D16: Definido
A17: Gestor de Solicitud | B17: Arquitectura orientada a eventos: quien tiene autoridad sobre la entidad (normalmente SuraHis) es quien emite el evento. | D17: Definido
A18: Gestor de Solicitud | B18: Integración con NEXO vía API (patrón API First) + exposición como MCP para agentes conversacionales (protocolo Agent-to-Agent). | D18: Definido
A19: Gestor de Solicitud | B19: Custodia temporal de historia clínica/orden médica en componente propio. | C19: Pendiente definir cifrado, acceso y retención. | D19: Por definir
A20: Gestor de Solicitud | B20: Riesgo técnico abierto: Super App en Google Cloud vs. resto del ecosistema en Azure. | D20: Riesgo abierto
A21: Gestor de Evaluación | B21: Consume la información ya extraída y estructurada por el gestor de Solicitud — no relee los documentos originales. | D21: Definido
A22: Gestor de Evaluación | B22: Debe consultar políticas/reglas a SuraHis manteniendo también reglas propias de agente (modelo híbrido). | C22: Línea de responsabilidad entre SuraHis y el gestor sin cerrar. | D22: Por cerrar | E22: Sigue abierto — tema profundizado 12-ago (ver nueva fila de Coordinación sobre dueño de las reglas); aplica también a Evaluación.
A23: Gestor de Evaluación | B23: Arquitectura híbrida multiagente propuesta: agente determinístico (coberturas/exclusiones) + agente de contexto (fraude/premium) + agente LLM (pertinencia médica). | D23: Propuesta preliminar
A24: Gestor de Evaluación | B24: Principio de diseño: la negación siempre debe ser determinística y trazable — nunca una decisión probabilística del LLM. | D24: Definido
A25: Gestor de Evaluación | B25: Hoy el evaluador humano usa 4 sistemas en paralelo (ADP, Global Web, ADR, P8) — meta explícita: unificar en una sola experiencia. | D25: Meta definida
A26: Gestor de Evaluación | B26: Es, junto con Solicitud, el gestor con mayor avance de diseño a la fecha del último seguimiento. | D26: En avance
A27: Gestor de Coordinación | B27: Arranca con motor 100% determinístico (reglas duras de elegibilidad, convenios, capacidad, ubicación y costo). | D27: Definido
A28: Gestor de Coordinación | B28: LLM reservado solo para casos no estructurados o de explicación — no es prioridad para el arranque. | D28: Definido
A29: Gestor de Coordinación | B29: Niveles de madurez agéntica: Nivel 1 determinístico → Nivel 2 + asistente explicativo → Nivel 3 agente autónomo (futuro, fuera de alcance actual). | D29: Definido (roadmap)
A30: Gestor de Coordinación | B30: Integración con prestadores externos preferiblemente vía API con retroalimentación de estados. | D30: Definido
A31: Gestor de Coordinación | B31: Bandeja "human in the loop" para casos donde ni las reglas ni la recomendación logran asignar un prestador. | D31: Definido
A32: Gestor de Coordinación | B32: Es uno de los gestores menos profundizados técnicamente a la fecha — "no se ha hecho zoom" todavía. | D32: Sin profundizar
A33: Gestor de Prestación | B33: Integración con clave dinámica (doble factor) como mecanismo de confirmación de la atención efectiva. | D33: En evaluación
A34: Gestor de Prestación | B34: Sin arquitectura técnica profundizada — reconocido explícitamente por el equipo de arquitectura. | D34: Sin profundizar
... A36: Gestor de Monitoreo (Torre de Control) | B36: El almacenamiento de eventos vive en un bus/componente dedicado, no exclusivo de este gestor — múltiples consumidores pueden leerlo. | D36: Definido
A37: Gestor de Monitoreo (Torre de Control) | B37: Pendiente definir si se expone una API única con filtrado por perfil o múltiples APIs por actor. | C37: Remitido al equipo de arquitectura. | D37: Por definir
A38: Gestor de Monitoreo (Torre de Control) | B38: Reto de integración en tiempo real con prestadores — hoy no existe (solo portal con interacción manual). | D38: Riesgo / reto abierto
A39: Gestor de Monitoreo (Torre de Control) | B39: Datalake de autorizaciones como entregable técnico del Release 3 (feb-abr 2027), con apoyo del arquitecto de datos. | D39: Planeado (Release 3)
A40: Gestor de Finalización | B40: Excluye explícitamente las "reglas de pago automático" (corresponden a Cuentas Médicas, fuera del MVP). | D40: Definido (fuera de alcance)
A41: Gestor de Finalización | B41: Sin arquitectura ni componentes técnicos definidos en ninguna de las fuentes revisadas a la fecha. | D41: Sin definir
A42: Transversal / Principios generales | B42: La interoperabilidad de historia clínica ya cuenta con una arquitectura 2.0 orientada a eventos (colas) a la que los gestores/Torre de Control pueden suscribirse directamente, en lugar de construir un componente de integración propio. | D42: Nuevo — Confirmado en sesión de Interoperabilidad 11-ago
A43: Gestor de Solicitud | B43: Modelo de datos de la bandeja de solicitud: entidad flexible con campos por defecto 'desconocido', bloqueo por exclusión mutua (mutex) con tiempo de vida (TTL) configurable, y generación de evento hacia el core solo al alcanzar completitud. | C43: TTL exacto pendiente de definir con negocio. | D43: Nuevo — Definido en sesión técnica 12-ago
A44: Gestor de Coordinación | B44: Pendiente definir el dueño y el mecanismo de sincronización de las reglas de direccionamiento/convenio: hoy viven en SuraHis (componente desacoplado, no un core monolítico); se evalúa si se replican hacia el gestor para dar mayor autonomía y capacidad agéntica. | C44: Negocio pidió mantener la capacidad de administrar/cambiar las reglas de convenio. | D44: Nuevo — Tema no claro, discutido 12-ago sin cierre | E44: Ver hoja de Pendientes y Conversaciones
A45: Gestor de Monitoreo (Torre de Control) | B45: Concepto en discusión: 'agente auditor' transversal que retroalimente a los gestores con aprendizaje continuo a partir de la trazabilidad (bandejas humanas, decisiones tomadas), para reducir con el tiempo la dependencia de intervención humana. | C45: Debate extenso sin resolver sobre si esto vive en Torre de Control o requiere comunicación entre agentes. | D45: Nuevo — Propuesta en discusión, sin decisión | E45: Ver hoja de Pendientes y Conversaciones — requiere sesión dedicada
A46: Gestor de Prestación | B46: Integración con la cola de eventos de interoperabilidad de historia clínica (arquitectura 2.0) para conocer si el servicio autorizado fue efectivamente atendido, sin construir un componente tecnológico nuevo en Gestores. | D46: Nuevo — Definido en sesión de Interoperabilidad 11-ago
A47: NUEVOS — definiciones de las sesiones del 18 al 20 de agosto de 2026 (40 requisitos no funcionales)
A48: Gestor de Solicitud | B48: Reutilizar el componente de Siniestro Integral a nivel de back para el primer release, en lugar de construir desde cero. | C48: Confirmar con el equipo técnico si el ajuste de reutilización es viable dentro de la ventana de dos meses. | D48: Nuevo — Definido en sesión 18-ago | E48: Diferido al Release 2 por capacidad del MVP de diciembre
A49: Gestor de Solicitud | B49: Reutilizar un lector de IA existente para la extracción documental: definir si se usa el de ADR o el que TT viene construyendo para historia clínica. | C49: Decisión pendiente entre ADR y el desarrollo de TT; impactada por el recorte de presupuesto del equipo de salud modular. | D49: Nuevo — Por definir en sesión 18-ago | E49: Diferido al Release 2 por capacidad del MVP de diciembre
A50: Gestor de Solicitud | B50: Definir si el radicado debe quedar garantizado en SuraHis desde el primer release, o si basta con que el gestor lo traiga hasta su frontera a la espera de una integración posterior. | C50: Pendiente técnico abierto en la sesión. | D50: Nuevo — Por definir en sesión 18-ago | E50: Diferido al Release 2 por capacidad del MVP de diciembre
A51: Canales / Front Externos | B51: Reutilizar los canales existentes hoy para el primer release, coordinando en paralelo la estimación de esfuerzo del equipo de canales. | C51: James no había entregado su propuesta de esfuerzo y tiempos al momento de la sesión. | D51: Nuevo — Definido en sesión 18-ago | E51: Coordinar con James si su cronograma es compatible con la ventana de dos meses
A52: Transversal / Principios generales | B52: Adoptar la metodología de estimar por cada gestor un escenario mínimo viable y uno completo/deseable, para sustentar ante los patrocinadores el alcance del primer release con datos comparables. | C52: Propuesta de Sebastián Sepúlveda; el mínimo viable de Evaluación tomaría cerca de cuatro meses. | D52: Nuevo — Definido en sesión 18-ago
A53: Transversal / Principios generales | B53: Confirmar el orden de dependencia entre gestores: cada gestor requiere el evento o salida del anterior, por lo que el Gestor de Solicitud es el punto de partida obligado del flujo. | D53: Nuevo — Definido en sesión 18-ago | E53: Sin la solicitud ningún otro gestor tiene insumo para operar
A54: Gestor de Solicitud | B54: Capa de agentes expertos: un agente por tipo de documento (historia clínica, orden médica, factura), enrutado según el tipo de solicitud. Esta capa es reutilizable y transversal a otros procesos y negocios. | D54: Nuevo — Definido en sesión 19-ago | E54: Diferido al Release 2 por capacidad del MVP de diciembre
A55: Gestor de Solicitud | B55: Capa de salida configurable: arma el resultado final según lo que cada core consumidor necesite. El mismo documento puede requerir campos distintos según el proceso que lo consuma (ej. autonomía no requiere CUPS pero sí resumen clínico y diagnóstico). | D55: Nuevo — Definido en sesión 19-ago | E55: Diferido al Release 2 por capacidad del MVP de diciembre
A56: Gestor de Solicitud | B56: Límite de auto-reparación de prompts del agente auditor: no puede ser totalmente autónomo sin acompañamiento humano, porque una corrección puede mejorar un campo y empeorar otro simultáneamente. | C56: Hasta qué punto tecnológicamente se puede asumir que un agente se auto-repare — calificado como el punto más complejo. | D56: Nuevo — Limitación tecnológica por resolver (19 y 20-ago) | E56: Pendiente de conversación con el equipo de IA (Julián / Daimer)
A57: Gestor de Solicitud | B57: Agente juez que valide en tiempo real usando un modelo distinto al del agente evaluado, para que el contraste tenga garantía real. | C57: Si el juez usa el mismo tipo de modelo que el agente evaluado no hay garantía; propuesta de usar dos modelos distintos. | D57: Nuevo — Propuesta en discusión (19-ago)
A58: Gestor de Solicitud | B58: Validar qué tipos de archivo puede almacenar el repositorio documental de los gestores (si admite ZIP o requiere descompresión previa). | C58: Falta validar en qué repositorio documental quedan los archivos. | D58: Nuevo — Abierto (19-ago)
A59: Gestor de Solicitud | B59: Flujo de activación confirmado: el Front informa a Siniestro Integral, este guarda la información dentro de SuraHis, y es SuraHis quien activa al gestor. | C59: Alinear con canales (James) cómo disponen hoy el envío de archivos desde sucursal virtual y el nuevo portal proveedor. | D59: Nuevo — Definido en sesión 19-ago | E59: Diferido al Release 2 por capacidad del MVP de diciembre
A60: Gestor de Evaluación | B60: Gobernanza de reglas: en vez de traer el motor de reglas al gestor, este consume una tool que invoca el motor de reglas del core, de forma que el día que exista un motor coreless solo haya que redirigir esa tool. | C60: Cómo se sostiene en el tiempo la relación de gobernanza entre el core (dueño de las reglas) y el gestor (que las opera). | D60: Nuevo — Definido en sesión 19-ago | E60: Estrategia Coreless: los cores como sistemas de registro, no de toma de decisiones
A61: Gestor de Evaluación | B61: SuraHis dispone de un módulo parametrizable de reglas duras que permite eliminarlas, modificarlas y ajustarlas; se mantiene como única fuente de verdad mediante carga en caché hacia el gestor. | C61: Pendiente consultar a Andrés Charry dónde viven exactamente las reglas del core y si se re-ejecutan al momento de crear la autorización. | D61: Nuevo — Definido parcialmente (19 y 20-ago) | E61: Preguntar por chat a Andrés Charry
A62: Gestor de Evaluación | B62: El Gestor de Evaluación no es transversal: está diseñado específicamente para autorizaciones de salud, aunque sus tres capas conceptuales (duplicados, evaluación, auditoría) sí pueden compartirse como patrón de diseño con otros procesos. | D62: Nuevo — Definido en sesión 19-ago
A63: Gestor de Monitoreo (Torre de Control) | B63: El Data Lake es una fuente más de información para la Torre de Control (solo lectura, no consumo bidireccional): viene curado y con calidad, pero con frescura mínima de T-1, por lo que no sirve para decisiones en tiempo real. | C63: Alcance exacto del consumo bidireccional del caso de negocio — escalado a Viviana. | D63: Nuevo — Definido en sesión 19-ago | E63: Corrige la capacidad 'consumo bidireccional del Data Lake' del caso de negocio original
A64: Gestor de Monitoreo (Torre de Control) | B64: Arquitectura tipo Lambda: vía rápida de eventos en tiempo real más vía lenta de productos del Data Lake, con capas de consolidación (vistas, sin capacidad agéntica), correlación (agéntica, genera insights) y toma de decisiones (alertar, priorizar, invocar herramientas hacia el core). | C64: Es difícil construir la capa de insight sin saber aún qué indicadores se quieren medir y controlar. | D64: Nuevo — Definido en sesiones 19 y 20-ago
A65: Gestor de Monitoreo (Torre de Control) | B65: La capa de ingesta y consolidación debe tener capacidad de streaming, no procesamiento por lotes. | D65: Nuevo — Definido en sesión 20-ago
A66: Gestor de Monitoreo (Torre de Control) | B66: La Torre de Control no tendrá un front propio de visualización al usuario final: la visibilidad diferenciada por actor es responsabilidad del frente de acceso/canales. | D66: Nuevo — Definido en sesión 19-ago
A67: Gestor de Monitoreo (Torre de Control) | B67: Trazar el límite entre las alertas que resuelve el propio core con un timer (ej. SLA vencido) y las que realmente requieren capacidad de la Torre de Control. | C67: Sin resolver en la sesión. | D67: Nuevo — Abierto (19-ago)
A68: Transversal / Principios generales | B68: Plataforma agéntica corporativa en construcción con el equipo de IA: Runtime agéntico (donde corren los agentes y sus tools) más Control Plane (gateway de consumo de LLM y gestión de prompts). Entregará parte —no todas— las capacidades de observabilidad genéricas que necesita la Torre de Control. | C68: El resto de capacidades de observabilidad deberá construirse específicamente para Gestores. | D68: Nuevo — Definido en sesión 19-ago
A69: Transversal / Principios generales | B69: Distinguir eventos funcionales (de las entidades de negocio, emitidos por su dueño) de eventos técnicos o de funcionamiento (emitidos por los propios gestores sobre cómo procesaron algo: modelo usado, prompt aplicado, resultado obtenido). | D69: Nuevo — Definido en sesión 19-ago | E69: Diferido al Release 2 por capacidad del MVP de diciembre
A70: Transversal / Principios generales | B70: La Solicitud y la Autorización hacen parte del core (SuraHis), por lo que SuraHis debe garantizar la emisión de eventos por cada cambio de estado. Global Web queda únicamente para expedición. | D70: Nuevo — Definido en sesión 19-ago | E70: El dueño de la entidad es quien emite el evento · Diferido al Release 2 por capacidad del MVP de diciembre
A71: Gestor de Monitoreo (Torre de Control) | B71: Nuevas entidades que deben emitir eventos hacia la Torre de Control: cuenta médica, orden de pago y cuentas por pagar. Esto implica que SAP también debe emitir eventos de desembolso para lograr trazabilidad completa desde la radicación de la autorización hasta el pago de la cuenta médica. | C71: Pendiente concretar la participación del equipo de observabilidad (Ángela/Angie, Carlos). | D71: Nuevo — Definido en sesión 20-ago
A72: Gestor de Finalización | B72: El Gestor de Finalización se representa en la arquitectura con líneas punteadas: no se implementa en el primer alcance de salud (donde la estrategia es que lo resuelva el core), pero queda mapeado en el roadmap para que el primer negocio que lo requiera dispare su implementación. | C72: ¿La postura de Viviana implica aceptación plena de que para salud la conciliación quede en el core, o mantiene que para otros negocios debe estar en gestores? | D72: Nuevo — Decisión provisional (20-ago) | E72: Validar con Vivi antes de cerrar la arquitectura
A73: Transversal / Principios generales | B73: Marco de buenas prácticas para sistemas agénticos: criterios de asertividad y trazabilidad para la medición de calidad de cada agente. | C73: Propuesta aditiva de Didier con Raúl; requiere refinamiento de ejemplos. | D73: Nuevo — Propuesta en discusión (20-ago) | E73: Diferido al Release 2 por capacidad del MVP de diciembre
A74: Transversal / Principios generales | B74: Versionamiento de sistemas agénticos, incluyendo la definición de si la data de reglas del core debe versionarse junto con el agente, y capacidad de rollback ante una liberación fallida. | C74: Si las reglas están en el core y el agente en el gestor, ¿cómo se versiona y qué implica para el rollback? | D74: Nuevo — Propuesta en discusión (20-ago)
A75: Transversal / Principios generales | B75: Concepto de 'function fitness': pruebas equivalentes a las de desarrollo de software aplicadas a agentes, para definir cuándo un modelo es maduro para liberarse a un cliente y en qué momento se considera autónomo. | D75: Nuevo — Propuesta en discusión (20-ago)
A76: Transversal / Principios generales | B76: Driver de dimensionamiento de agentes: parametrizar la complejidad de cada agente para aproximar con mayor certidumbre el costo de su implementación. | C76: Borrador en construcción con apoyo de NTT Data y Diego; pendiente de compartir antes del ejercicio de estimación. | D76: Nuevo — En construcción (20-ago)
A77: Transversal / Principios generales | B77: Conformación y onboarding del equipo: definición de squads, roles y dedicaciones, y capacitación del personal nuevo en el dominio de autorizaciones de salud. | C77: Armar y capacitar un equipo nuevo puede tomar más de la mitad de septiembre. | D77: Sprint 0 — Preparación | E77: Riesgo señalado en la sesión del 18-ago
A78: Transversal / Principios generales | B78: Habilitación de ambientes de desarrollo y pruebas, infraestructura base, repositorios, pipelines de CI/CD y estándares de código. | D78: Sprint 0 — Preparación
A79: Transversal / Principios generales | B79: Configuración del Runtime agéntico y del Control Plane corporativo (gateway de consumo de LLM y gestión de prompts) para el equipo de Gestores. | C79: Depende del avance de la plataforma agéntica corporativa que construye el equipo de IA. | D79: Sprint 0 — Preparación
A80: Transversal / Principios generales | B80: Elaboración del borrador del catálogo de eventos y de los contratos de API que servirán de base al Release 1. | D80: Sprint 0 — Preparación | E80: Camino crítico: sin este contrato ningún squad puede construir
A81: Transversal / Principios generales | B81: Acuerdo formal de capacidad y disponibilidad con el equipo de SuraHis para la exposición de APIs y eventos del core. | C81: Dependencia crítica número uno del proyecto. | D81: Sprint 0 — Preparación | E81: Requiere compromiso explícito con Andrés Charry
A82: Transversal / Principios generales | B82: Transferencia de contexto funcional al equipo técnico: proceso actual de autorizaciones, modelo de estados, entidades y decisiones de arquitectura ya tomadas. | D82: Sprint 0 — Preparación
A83: Transversal / Principios generales | B83: Cierre del ejercicio de dimensionamiento de agentes y estimación de costo, aplicando el driver construido con NTT Data. | C83: El driver estaba en borrador al 20-ago. | D83: Sprint 0 — Preparación | E83: Ejercicio iniciado el 21-ago de 1:30 p.m. a 5:00 p.m.
A84: Gestor de Solicitud | B84: Decisión técnica del lector de IA a reutilizar (ADR vs. desarrollo de TT) y prueba de concepto de la extracción documental sobre documentos reales. | C84: Impactada por el recorte de presupuesto del equipo de salud modular. | D84: Sprint 0 — Preparación
A85: Transversal / Principios generales | B85: Definición del umbral de asertividad y de las métricas de calidad de los agentes que se aplicarán desde el Release 1. | C85: Valor exacto del umbral por definir. | D85: Sprint 0 — Preparación
A86: Canales / Front Externos | B86: Confirmación del alcance del Release 1 con negocio y con el equipo de canales: rol y canal específicos, y compatibilidad de cronogramas. | C86: James no había entregado su estimación de esfuerzo al 18-ago. | D86: Sprint 0 — Preparación
A87: Transversal / Principios generales | B87: Validación con el equipo técnico de los tallajes y estimaciones preliminares, y ajuste del backlog del Release 1 antes de iniciar la implementación. | D87: Sprint 0 — Preparación

Sheet Pendientes
A1: PENDIENTES Y CONVERSACIONES ABIERTAS
A2: 53 pendientes por gestor. La columna 'Nuevo' marca lo que salió de la sesión del 10-ago-2026.
A4: Gestor / Frente | B4: Pendiente | C4: Nuevo (10-ago-2026) | D4: Estado | E4: Fecha objetivo | F4: Decisión / Seguimiento
A5: Gestor de Solicitud | B5: Definir si el backend/bandeja de Solicitudes vive dentro de SuraHis o del gestor. | C5: No | D5: Abierto — requiere sesión formal con Andrés Charry (SuraHis)
A6: Gestor de Solicitud | B6: Definir si la comunicación con SuraHis es síncrona (REST) o por eventos/colas. | C6: No | D6: Abierto
A7: Gestor de Solicitud | B7: Definir si el gestor requiere base de datos propia o si toda la información vive en SuraHis. | C7: No | D7: Abierto
A8: Gestor de Solicitud | B8: Definir si se reutiliza también el front de Siniestro Integral (el back ya está acordado). | C8: No | D8: Abierto
A9: Gestor de Solicitud | B9: Cerrar con el equipo de Canales el detalle completo de qué puede hacer el cliente por cada canal. | C9: No | D9: Abierto
A10: Gestor de Solicitud | B10: Levantar la tabla completa de vigencia documental por tipo de examen/tratamiento. | C10: No | D10: Abierto (sin fecha reportada)
A11: Gestor de Solicitud | B11: Definir política de retención/borrado de la información clínica extraída y almacenada temporalmente. | C11: No | D11: Abierto
A12: Gestor de Solicitud | B12: Definir la estrategia final de almacenamiento documental (P8 vs. alternativa Oracle con IA embebida). | C12: No | D12: Abierto (PoC en curso)
A13: Gestor de Solicitud | B13: Definir si se requiere agente conversacional en canales digitales (SDP/WhatsApp) en esta fase. | C13: No | D13: Abierto
A14: Gestor de Solicitud | B14: Resolver la incompatibilidad de nube (Super App en Google Cloud vs. resto del ecosistema en Azure). | C14: No | D14: Abierto
A15: Gestor de Solicitud | B15: Validar con James el alcance real del agente de prevalidación de documentos en el Front (componente no bloqueante). | C15: Sí | D15: Abierto | E15: 11-ago-2026 (espacio ya agendado)
A16: Gestor de Evaluación | B16: Definir la línea exacta de responsabilidad entre SuraHis (reglas del core) y el gestor (reglas propias del agente). | C16: No | D16: Abierto
A17: Gestor de Evaluación | B17: Definir si el nivel de escalamiento (2/3/4) se fusiona dentro de Evaluación o queda en un gestor de Asignación independiente. | C17: No | D17: Abierto
A18: Gestor de Evaluación | B18: Definir si el agente necesita memoria histórica del asegurado. | C18: No | D18: Abierto (pendiente con negocio)
A19: Gestor de Evaluación | B19: Resolver las discrepancias de exclusiones no sincronizadas entre ADP y Global Web. | C19: No | D19: Abierto (validar con Suscripción)
A20: Gestor de Evaluación | B20: Definir la estandarización/automatización de observaciones obligatorias por tipo de servicio. | C20: No | D20: Abierto
A21: Gestor de Evaluación | B21: Validar con SuraHis la flexibilidad real de configuración de las reglas de asignación. | C21: No | D21: Abierto
A22: Gestor de Evaluación | B22: Profundizar el diseño técnico concreto del sistema híbrido multiagente. | C22: No | D22: Abierto (hoy solo propuesta preliminar)
A23: Gestor de Evaluación | B23: Definir con el equipo médico/de negocio qué servicios pueden autorizarse más de una vez en una ventana de tiempo y cuáles no (base de las reglas de duplicidad). | C23: Sí | D23: Abierto
A24: Gestor de Coordinación | B24: Construir la lista de criterios de priorización de prestadores. | C24: No | D24: Abierto
A25: Gestor de Coordinación | B25: Definir el indicador de "suficiencia de la red". | C25: No | D25: Abierto
A26: Gestor de Coordinación | B26: Validar con SuraHis el mecanismo de asignación manual cuando no hay convenio/prestador disponible. | C26: No | D26: Abierto
A27: Gestor de Coordinación | B27: Definir responsable y mecanismo de notificación a canales tras la coordinación (¿directo o vía Monitoreo?). | C27: No | D27: Pospuesto explícitamente
... A35: Gestor de Prestación | B35: Definir si se va a hacer seguimiento a la prestación de servicios autorizados por integralidad en EPS Sura. | C35: No | D35: En "zona de parqueo"
A36: Gestor de Prestación | B36: No se alcanzó a mapear las capacidades esperadas de la Torre de Control para este gestor en la sesión del 10-ago. | C36: Sí | D36: Abierto | E36: 11-ago-2026 (continúa la sesión)
A37: Gestor de Monitoreo (Torre de Control) | B37: Diseñar el diagrama de estados completo de todos los gestores. | C37: No | D37: Abierto
A38: Gestor de Monitoreo (Torre de Control) | B38: Definir el mecanismo/nombre de la capa de retroalimentación/auditoría hacia los demás gestores. | C38: No | D38: Abierto
A39: Gestor de Monitoreo (Torre de Control) | B39: Resolver el reto de integración en tiempo real con prestadores. | C39: No | D39: Abierto
A40: Gestor de Monitoreo (Torre de Control) | B40: Definir dónde reside la decisión de qué estados se notifican proactivamente vs. cuáles solo van al historial. | C40: No | D40: Abierto
A41: Gestor de Monitoreo (Torre de Control) | B41: No se ha hecho sesión de estructuración dedicada — identificado como "especialmente grande". | C41: No | D41: Sin abordar (a la fecha del PPT)
A42: Gestor de Monitoreo (Torre de Control) | B42: ¿La Torre de Control únicamente genera el evento, o hay algún escenario en que debería notificar directamente? | C42: Sí | D42: Abierto
A43: Gestor de Monitoreo (Torre de Control) | B43: ¿Cómo recibe en la práctica el equipo de canales (James) los eventos de la Torre de Control para disparar la notificación? | C43: Sí | D43: Abierto | E43: 11-ago-2026 (espacio agendado con James)
A44: Gestor de Monitoreo (Torre de Control) | B44: ¿La redistribución de casos cuando un evaluador no está disponible es responsabilidad exclusiva de SuraHis o también de la Torre de Control? | C44: Sí | D44: Abierto (posiciones distintas en la sesión, sin cerrar)
A45: Gestor de Monitoreo (Torre de Control) | B45: Cerrar el punto de notificaciones/alertas entre la Torre de Control y el Core para el gestor de Asignación. | C45: Sí | D45: Abierto — reconocido explícitamente al cierre de la sesión del 10-ago | E45: 11-ago-2026 (continúa la sesión)
A46: Gestor de Monitoreo (Torre de Control) | B46: No se alcanzó a mapear las capacidades esperadas de la Torre de Control para el gestor de Finalización en la sesión del 10-ago. | C46: Sí | D46: Abierto | E46: 11-ago-2026 (continúa la sesión)
A47: Gestor de Finalización | B47: Es el gestor con menor nivel de definición de los 6 — sin sesión de estructuración dedicada en todo el período revisado. | C47: No | D47: Sin iniciar
A48: Gestor de Finalización | B48: Definir si es un "agente" puro o mixto (reglas de cruce de costos + agente lector de soportes). | C48: No | D48: Abierto
A49: Gestor de Finalización | B49: Definir el alcance exacto de la conexión con Cuentas Médicas. | C49: No | D49: Abierto
A50: Gestor de Finalización | B50: Coordinar con las iniciativas paralelas de IA de conciliación de cuentas médicas para evitar duplicidad de esfuerzo. | C50: No | D50: Abierto
A51: Transversal / Principios generales | B51: Consolidar y enviar formalmente a SuraHis el listado único de supuestos/responsabilidades a validar. | C51: No | D51: Abierto
A52: Transversal / Principios generales | B52: Definir con Camilo Rodríguez y Ana el tiempo de sus arquitectos en el proyecto. | C52: No | D52: Abierto
A53: Transversal / Principios generales | B53: Definir con NEXO (Carlos Carmona) la fecha exacta de integración. | C53: No | D53: Abierto
A54: Transversal / Principios generales | B54: Definir el gestor/función de Fraude: si permanece independiente o se absorbe dentro de Evaluación. | C54: No | D54: Abierto
A55: Transversal / Principios generales | B55: Definir el modelo de integración (comando vs. evento) caso de uso por caso de uso, con el equipo de arquitectura. | C55: No | D55: Abierto
A56: Transversal / Principios generales | B56: Resolver la desalineación de expectativas señalada por Viviana Monsalve sobre referenciar soluciones de mercado ya existentes. | C56: No | D56: Abierto
A57: Transversal / Principios generales | B57: Sesión de seguimiento general del proyecto y sesión de verificación con SuraHis. | C57: Sí | D57: Abierto | E57: 11-ago-2026

Sheet Riesgos
A1: RIESGOS IDENTIFICADOS POR CATEGORÍA
A2: 16 riesgos agrupados en cuatro categorías.
A4: Categoría | B4: Riesgo identificado | C4: Nivel de impacto | D4: Estado / Mitigación | E4: Decisión / Seguimiento
A5: Tecnología y Arquitectura | B5: Dependencia crítica de SuraHis: el proyecto solo funciona si los cores exponen información vía API a tiempo; SuraHis estima 6-7 meses de implementación.
A6: Tecnología y Arquitectura | B6: Riesgo de romper la filosofía "coreless" si el core termina absorbiendo la trazabilidad y la lógica de los gestores.
A7: Tecnología y Arquitectura | B7: Alto acoplamiento hoy en el orquestador de Siniestro Integral, que se reutiliza como base del gestor de Solicitud.
A8: Tecnología y Arquitectura | B8: Incompatibilidad de nube: Super App en Google Cloud vs. resto del ecosistema en Azure.
A9: Inteligencia Artificial | B9: Riesgo de escalabilidad/resiliencia del core y dependencia crítica de P8 para la custodia documental.
A10: Inteligencia Artificial | B10: Riesgo de alucinación o decisión probabilística del LLM en puntos críticos como la negación de servicios.
A11: Inteligencia Artificial | B11: Riesgo reputacional/regulatorio (caso de referencia internacional): automatizar sin cuidar calidad y equidad generó demandas y sanciones en el sector.
A12: Inteligencia Artificial | B12: Presión regulatoria creciente sobre explicabilidad de IA (EU AI Act, NAIC, Colombia) — toda decisión debe ser auditable y trazable.
A13: Operación y Proceso | B13: Fraude estructural no mitigado hoy: no se verifica que el servicio facturado se haya prestado realmente.
A14: Operación y Proceso | B14: Interoperabilidad clínica limitada hoy a "consulta externa" (~3.248 prestadores) — riesgo de diseño parcial sin un plan B claro.
A15: Operación y Proceso | B15: Riesgo de cronograma: a la fecha, solo 2 de 6 gestores (Solicitud y Evaluación) estaban profundizados, con cierre comprometido el 27-ago.
A16: Operación y Proceso | B16: Falta de capacidad dedicada (vs. "por demanda") de los equipos de canales, core, datos e IA; vacante de arquitecto de datos.
... A20: Cambio, Capacidad y Financiero | B20: Riesgo de duplicar esfuerzo con iniciativas paralelas de IA (piloto de conciliación de cuentas médicas).

Sheet Listas
A1: Catálogos de referencia
A3: Priorización (MoSCoW) | B3: Talla | C3: Release | D3: Estado de refinamiento | E3: Squad | F3: Tipo de requisito
A4: Debe tener | B4: XS · 1 día | C4: Sprint 0 | D4: Por confirmar talla | E4: Plataforma | F4: RF · Requisito Funcional
A5: Debería tener | B5: S · 3 días · 1/4 sprint | C5: Release 1 | D5: Talla confirmada | E5: Solicitud | F5: RNF · Requisito No Funcional
A6: Podría tener | B6: M · 5 días · 1/2 sprint | C6: Release 2 | D6: Refinada | E6: Canales
A7: No debería | B7: L · 10 días · 1 sprint | C7: Release 3 | D7: Descartada | E7: Evaluación
B8: XL · 20 días · 2 sprints | C8: Fase posterior | E8: Coordinación
B9: XXL · 30 días · 3+ sprints | E9: Torre de Control
E10: Prestación
E11: Finalización
